{"IdMax":"0","LimiteNbChar":-1,"LimitCharExceeded_Trial":false,"Map_PosSol":{"Cor":[{"IndexPar":0,"LeftPos":0,"RightPos":5,"MotSolution":{"Start_Pos":0,"End_Pos":5,"WordSt":"Sa va","WordDisplayed":"Sa va","IdPhrase":"","Id":"0","IdFin":"","Type":0,"vectSolution":[{"Left":"Să vă","Right":"Să vă"}],"ExplicationSolution":" Corectez lipsa diacritice.","EstSuggestion":false,"Vect_SolId":[],"IsUnknownProperNoun":false,"IsAnothA":false,"VectOtherResults":[]}},{"IndexPar":0,"LeftPos":23,"RightPos":38,"MotSolution":{"Start_Pos":23,"End_Pos":38,"WordSt":"si sa ziceti ca","WordDisplayed":"si sa ziceti ca","IdPhrase":"","Id":"1","IdFin":"","Type":0,"vectSolution":[{"Left":"și să ziceți că","Right":"și să ziceți că"}],"ExplicationSolution":" Adaug diacritice și corectez lipsa conjuncției coordonatoare \"că\".","EstSuggestion":false,"Vect_SolId":[],"IsUnknownProperNoun":false,"IsAnothA":false,"VectOtherResults":[]}},{"IndexPar":0,"LeftPos":41,"RightPos":48,"MotSolution":{"Start_Pos":41,"End_Pos":48,"WordSt":"palarie","WordDisplayed":"palarie","IdPhrase":"","Id":"2","IdFin":"","Type":0,"vectSolution":[{"Left":"pălărie","Right":"pălărie"}],"ExplicationSolution":" Corectez lipsa diacritice.","EstSuggestion":false,"Vect_SolId":[],"IsUnknownProperNoun":false,"IsAnothA":false,"VectOtherResults":[]}},{"IndexPar":0,"LeftPos":52,"RightPos":59,"MotSolution":{"Start_Pos":52,"End_Pos":59,"WordSt":"soareVa","WordDisplayed":"soareVa","IdPhrase":"","Id":"3","IdFin":"","Type":0,"vectSolution":[{"Left":"soare. Vă","Right":"soare. Vă"}],"ExplicationSolution":" Înlocuiesc lipsa de punctuație (punct) cu punct și spațiu, corectând de asemenea, lipsa diacritice.","EstSuggestion":false,"Vect_SolId":[],"IsUnknownProperNoun":false,"IsAnothA":false,"VectOtherResults":[]}},{"IndexPar":0,"LeftPos":62,"RightPos":67,"MotSolution":{"Start_Pos":62,"End_Pos":67,"WordSt":"pofta","WordDisplayed":"pofta","IdPhrase":"","Id":"4","IdFin":"","Type":0,"vectSolution":[{"Left":"poftă,","Right":"poftă,"}],"ExplicationSolution":" Adaug diacritice și corectez lipsa de punctuație cu virgulă.","EstSuggestion":false,"Vect_SolId":[],"IsUnknownProperNoun":false,"IsAnothA":false,"VectOtherResults":[]}},{"IndexPar":0,"LeftPos":81,"RightPos":86,"MotSolution":{"Start_Pos":81,"End_Pos":86,"WordSt":"Stati","WordDisplayed":"Stati","IdPhrase":"","Id":"5","IdFin":"","Type":0,"vectSolution":[{"Left":"Stați","Right":"Stați"}],"ExplicationSolution":" Corectez lipsa diacritice.","EstSuggestion":false,"Vect_SolId":[],"IsUnknownProperNoun":false,"IsAnothA":false,"VectOtherResults":[]}},{"IndexPar":0,"LeftPos":90,"RightPos":96,"MotSolution":{"Start_Pos":90,"End_Pos":96,"WordSt":"dintii","WordDisplayed":"dintii","IdPhrase":"","Id":"6","IdFin":"","Type":0,"vectSolution":[{"Left":"dinții","Right":"dinții"}],"ExplicationSolution":" Corectez lipsa diacritice.","EstSuggestion":false,"Vect_SolId":[],"IsUnknownProperNoun":false,"IsAnothA":false,"VectOtherResults":[]}},{"IndexPar":0,"LeftPos":105,"RightPos":125,"MotSolution":{"Start_Pos":105,"End_Pos":125,"WordSt":"ca, cacat veti primi","WordDisplayed":"ca, cacat veti primi","IdPhrase":"","Id":"7","IdFin":"","Type":0,"vectSolution":[{"Left":"că, rahat veți primi!","Right":"că, rahat veți primi!"}],"ExplicationSolution":" Corectez greșeala de punctuație (virgulă în loc de semnul exclamării) și înlocuiesc cuvântul vulgar (\"cacat\") cu sinonimul mai puțin ofensator (\"rahat\"). Adaug un semnul exclamării la final pentru a sublinia.","EstSuggestion":false,"Vect_SolId":[],"IsUnknownProperNoun":false,"IsAnothA":false,"VectOtherResults":[]}},{"IndexPar":0,"LeftPos":127,"RightPos":131,"MotSolution":{"Start_Pos":127,"End_Pos":131,"WordSt":"Daca","WordDisplayed":"Daca","IdPhrase":"","Id":"8","IdFin":"","Type":0,"vectSolution":[{"Left":"Dacă","Right":"Dacă"}],"ExplicationSolution":" Corectez lipsa diacritice.","EstSuggestion":false,"Vect_SolId":[],"IsUnknownProperNoun":false,"IsAnothA":false,"VectOtherResults":[]}},{"IndexPar":0,"LeftPos":140,"RightPos":144,"MotSolution":{"Start_Pos":140,"End_Pos":144,"WordSt":"capu","WordDisplayed":"capu","IdPhrase":"","Id":"9","IdFin":"","Type":0,"vectSolution":[{"Left":"capul","Right":"capul"}],"ExplicationSolution":" Corectez forma substantivului.","EstSuggestion":false,"Vect_SolId":[],"IsUnknownProperNoun":false,"IsAnothA":false,"VectOtherResults":[]}},{"IndexPar":0,"LeftPos":148,"RightPos":152,"MotSolution":{"Start_Pos":148,"End_Pos":152,"WordSt":"fier","WordDisplayed":"fier","IdPhrase":"","Id":"10","IdFin":"","Type":0,"vectSolution":[{"Left":"fier,","Right":"fier,"}],"ExplicationSolution":"Adaug virgulă după substantiv, conform regulilor de punctuație, deoarece urmează o apoziție.","EstSuggestion":false,"Vect_SolId":[],"IsUnknownProperNoun":false,"IsAnothA":false,"VectOtherResults":[]}},{"IndexPar":0,"LeftPos":166,"RightPos":170,"MotSolution":{"Start_Pos":166,"End_Pos":170,"WordSt":"cata","WordDisplayed":"cata","IdPhrase":"","Id":"11","IdFin":"","Type":0,"vectSolution":[{"Left":"câtă","Right":"câtă"}],"ExplicationSolution":"Corectez lipsa diacritice.","EstSuggestion":false,"Vect_SolId":[],"IsUnknownProperNoun":false,"IsAnothA":false,"VectOtherResults":[]}},{"IndexPar":0,"LeftPos":179,"RightPos":187,"MotSolution":{"Start_Pos":179,"End_Pos":187,"WordSt":"luat, am","WordDisplayed":"luat, am","IdPhrase":"","Id":"12","IdFin":"","Type":0,"vectSolution":[{"Left":"luat. Am","Right":"luat. Am"}],"ExplicationSolution":"Înlocuiesc virgula cu punct, deoarece urmează o nouă propoziție.","EstSuggestion":false,"Vect_SolId":[],"IsUnknownProperNoun":false,"IsAnothA":false,"VectOtherResults":[]}},{"IndexPar":0,"LeftPos":197,"RightPos":199,"MotSolution":{"Start_Pos":197,"End_Pos":199,"WordSt":"ca","WordDisplayed":"ca","IdPhrase":"","Id":"13","IdFin":"","Type":0,"vectSolution":[{"Left":"că","Right":"că"}],"ExplicationSolution":"Corectez lipsa diacritice.","EstSuggestion":false,"Vect_SolId":[],"IsUnknownProperNoun":false,"IsAnothA":false,"VectOtherResults":[]}},{"IndexPar":0,"LeftPos":203,"RightPos":216,"MotSolution":{"Start_Pos":203,"End_Pos":216,"WordSt":"ramas inca in","WordDisplayed":"ramas inca in","IdPhrase":"","Id":"14","IdFin":"","Type":0,"vectSolution":[{"Left":"rămas încă în","Right":"rămas încă în"}],"ExplicationSolution":"Corectez greșeala de ortografie (lipsă cratimă) și corectez lipsa diacritice.","EstSuggestion":false,"Vect_SolId":[],"IsUnknownProperNoun":false,"IsAnothA":false,"VectOtherResults":[]}},{"IndexPar":0,"LeftPos":228,"RightPos":240,"MotSolution":{"Start_Pos":228,"End_Pos":240,"WordSt":"spermatozoid","WordDisplayed":"spermatozoid","IdPhrase":"","Id":"15","IdFin":"","Type":0,"vectSolution":[{"Left":"spermatozoid.","Right":"spermatozoid."}],"ExplicationSolution":"Adaug punct la finalul frazei.","EstSuggestion":false,"Vect_SolId":[],"IsUnknownProperNoun":false,"IsAnothA":false,"VectOtherResults":[]}},{"IndexPar":0,"LeftPos":263,"RightPos":281,"MotSolution":{"Start_Pos":263,"End_Pos":281,"WordSt":"pitici nu ? uite-l","WordDisplayed":"pitici nu ? uite-l","IdPhrase":"","Id":"16","IdFin":"","Type":0,"vectSolution":[{"Left":"pitici, nu? Uite-l","Right":"pitici, nu? Uite-l"}],"ExplicationSolution":"Corectez lipsa de punctuație (semnul întrebării + spațiu incorect) și înlocuiesc virgula lipsă.","EstSuggestion":false,"Vect_SolId":[],"IsUnknownProperNoun":false,"IsAnothA":false,"VectOtherResults":[]}},{"IndexPar":0,"LeftPos":285,"RightPos":293,"MotSolution":{"Start_Pos":285,"End_Pos":293,"WordSt":"Mutulica","WordDisplayed":"Mutulica","IdPhrase":"","Id":"17","IdFin":"","Type":0,"vectSolution":[{"Left":"Mutulică,","Right":"Mutulică,"}],"ExplicationSolution":"Corectez lipsa diacritice și adaug virgulă.","EstSuggestion":false,"Vect_SolId":[],"IsUnknownProperNoun":false,"IsAnothA":false,"VectOtherResults":[]}},{"IndexPar":0,"LeftPos":298,"RightPos":313,"MotSolution":{"Start_Pos":298,"End_Pos":313,"WordSt":"inecat in balta","WordDisplayed":"inecat in balta","IdPhrase":"","Id":"18","IdFin":"","Type":0,"vectSolution":[{"Left":"înecat în baltă","Right":"înecat în baltă"}],"ExplicationSolution":"Corectez lipsa diacritice.","EstSuggestion":false,"Vect_SolId":[],"IsUnknownProperNoun":false,"IsAnothA":false,"VectOtherResults":[]}},{"IndexPar":0,"LeftPos":334,"RightPos":340,"MotSolution":{"Start_Pos":334,"End_Pos":340,"WordSt":"ma-tii","WordDisplayed":"ma-tii","IdPhrase":"","Id":"19","IdFin":"","Type":0,"vectSolution":[{"Left":"ma-tii.","Right":"ma-tii."}],"ExplicationSolution":"Adaug punct la finalul frazei.","EstSuggestion":false,"Vect_SolId":[],"IsUnknownProperNoun":false,"IsAnothA":false,"VectOtherResults":[]}},{"IndexPar":0,"LeftPos":346,"RightPos":487,"MotSolution":{"Start_Pos":346,"End_Pos":487,"WordSt":"sloboziților,zabalosilor cocliților rataților obosiților martalogilor,fomistilor cocarjaților sugacilor retardaților,chisaților,labagiilor si","WordDisplayed":"sloboziților,zabalosilor cocliților rataților obosiților martalogilor,fomistilor cocarjaților sugacilor retardaților,chisaților,labagiilor si","IdPhrase":"","Id":"20","IdFin":"","Type":0,"vectSolution":[{"Left":"sloboziților, zabalosilor, cocliților, rataților, obosiților, martalogilor, fomiștilor, cocârjaților, sugacilor, retardaților, chișaților, labagiilor și","Right":"sloboziților, zabalosilor, cocliților, rataților, obosiților, martalogilor, fomiștilor, cocârjaților, sugacilor, retardaților, chișaților, labagiilor și"}],"ExplicationSolution":"Corectez lipsa diacriticelor.","EstSuggestion":false,"Vect_SolId":[],"IsUnknownProperNoun":false,"IsAnothA":false,"VectOtherResults":[]}},{"IndexPar":0,"LeftPos":546,"RightPos":548,"MotSolution":{"Start_Pos":546,"End_Pos":548,"WordSt":"si","WordDisplayed":"si","IdPhrase":"","Id":"21","IdFin":"","Type":0,"vectSolution":[{"Left":"și","Right":"și"}],"ExplicationSolution":"Corectez lipsa diacritice.","EstSuggestion":false,"Vect_SolId":[],"IsUnknownProperNoun":false,"IsAnothA":false,"VectOtherResults":[]}},{"IndexPar":0,"LeftPos":566,"RightPos":578,"MotSolution":{"Start_Pos":566,"End_Pos":578,"WordSt":"veniti sa va","WordDisplayed":"veniti sa va","IdPhrase":"","Id":"22","IdFin":"","Type":0,"vectSolution":[{"Left":"veniți să vă","Right":"veniți să vă"}],"ExplicationSolution":"Corectez lipsa diacritice.","EstSuggestion":false,"Vect_SolId":[],"IsUnknownProperNoun":false,"IsAnothA":false,"VectOtherResults":[]}},{"IndexPar":0,"LeftPos":603,"RightPos":616,"MotSolution":{"Start_Pos":603,"End_Pos":616,"WordSt":"sa va largesc","WordDisplayed":"sa va largesc","IdPhrase":"","Id":"23","IdFin":"","Type":0,"vectSolution":[{"Left":"să vă lărgesc","Right":"să vă lărgesc"}],"ExplicationSolution":"Corectez lipsa diacritice.","EstSuggestion":false,"Vect_SolId":[],"IsUnknownProperNoun":false,"IsAnothA":false,"VectOtherResults":[]}},{"IndexPar":0,"LeftPos":625,"RightPos":627,"MotSolution":{"Start_Pos":625,"End_Pos":627,"WordSt":"sa","WordDisplayed":"sa","IdPhrase":"","Id":"24","IdFin":"","Type":0,"vectSolution":[{"Left":"să","Right":"să"}],"ExplicationSolution":"Corectez lipsa diacritice.","EstSuggestion":false,"Vect_SolId":[],"IsUnknownProperNoun":false,"IsAnothA":false,"VectOtherResults":[]}},{"IndexPar":0,"LeftPos":634,"RightPos":638,"MotSolution":{"Start_Pos":634,"End_Pos":638,"WordSt":"pula","WordDisplayed":"pula","IdPhrase":"","Id":"25","IdFin":"","Type":0,"vectSolution":[{"Left":"pula!","Right":"pula!"}],"ExplicationSolution":"Adaug un semnul exclamării la final pentru a sublinia.","EstSuggestion":false,"Vect_SolId":[],"IsUnknownProperNoun":false,"IsAnothA":false,"VectOtherResults":[]}},{"IndexPar":0,"LeftPos":668,"RightPos":673,"MotSolution":{"Start_Pos":668,"End_Pos":673,"WordSt":"varza","WordDisplayed":"varza","IdPhrase":"","Id":"26","IdFin":"","Type":0,"vectSolution":[{"Left":"varză","Right":"varză"}],"ExplicationSolution":"Corectez lipsa diacritice.","EstSuggestion":false,"Vect_SolId":[],"IsUnknownProperNoun":false,"IsAnothA":false,"VectOtherResults":[]}},{"IndexPar":0,"LeftPos":677,"RightPos":696,"MotSolution":{"Start_Pos":677,"End_Pos":696,"WordSt":"cotoru in cu aiurea","WordDisplayed":"cotoru in cu aiurea","IdPhrase":"","Id":"27","IdFin":"","Type":0,"vectSolution":[{"Left":"cotorul aiurea!","Right":"cotorul aiurea!"}],"ExplicationSolution":"Corectez exprimarea și adaug un semnul exclamării la final pentru a sublinia.","EstSuggestion":false,"Vect_SolId":[],"IsUnknownProperNoun":false,"IsAnothA":false,"VectOtherResults":[]}},{"IndexPar":0,"LeftPos":701,"RightPos":703,"MotSolution":{"Start_Pos":701,"End_Pos":703,"WordSt":"si","WordDisplayed":"si","IdPhrase":"","Id":"28","IdFin":"","Type":0,"vectSolution":[{"Left":"și","Right":"și"}],"ExplicationSolution":"Corectez lipsa diacritice.","EstSuggestion":false,"Vect_SolId":[],"IsUnknownProperNoun":false,"IsAnothA":false,"VectOtherResults":[]}},{"IndexPar":0,"LeftPos":707,"RightPos":723,"MotSolution":{"Start_Pos":707,"End_Pos":723,"WordSt":"mata sa va luati","WordDisplayed":"mata sa va luati","IdPhrase":"","Id":"29","IdFin":"","Type":0,"vectSolution":[{"Left":"ma-ta să vă luați","Right":"ma-ta să vă luați"}],"ExplicationSolution":"Corectez greșeala de exprimare cu referire la persoană și corectez lipsa diacritice.","EstSuggestion":false,"Vect_SolId":[],"IsUnknownProperNoun":false,"IsAnothA":false,"VectOtherResults":[]}},{"IndexPar":0,"LeftPos":741,"RightPos":763,"MotSolution":{"Start_Pos":741,"End_Pos":763,"WordSt":"sa veniti sa-mi sugeti","WordDisplayed":"sa veniti sa-mi sugeti","IdPhrase":"","Id":"30","IdFin":"","Type":0,"vectSolution":[{"Left":"să veniți să-mi sugeți","Right":"să veniți să-mi sugeți"}],"ExplicationSolution":"Corectez lipsa diacritice.","EstSuggestion":false,"Vect_SolId":[],"IsUnknownProperNoun":false,"IsAnothA":false,"VectOtherResults":[]}},{"IndexPar":0,"LeftPos":776,"RightPos":780,"MotSolution":{"Start_Pos":776,"End_Pos":780,"WordSt":"alta","WordDisplayed":"alta","IdPhrase":"","Id":"31","IdFin":"","Type":0,"vectSolution":[{"Left":"alta,","Right":"alta,"}],"ExplicationSolution":"Adaug virgulă după cuvânt, conform regulilor de punctuație.","EstSuggestion":false,"Vect_SolId":[],"IsUnknownProperNoun":false,"IsAnothA":false,"VectOtherResults":[]}},{"IndexPar":0,"LeftPos":785,"RightPos":792,"MotSolution":{"Start_Pos":785,"End_Pos":792,"WordSt":"inainte","WordDisplayed":"inainte","IdPhrase":"","Id":"32","IdFin":"","Type":0,"vectSolution":[{"Left":"înainte","Right":"înainte"}],"ExplicationSolution":"Corectez lipsa diacritice.","EstSuggestion":false,"Vect_SolId":[],"IsUnknownProperNoun":false,"IsAnothA":false,"VectOtherResults":[]}},{"IndexPar":0,"LeftPos":816,"RightPos":838,"MotSolution":{"Start_Pos":816,"End_Pos":838,"WordSt":"si toti mortii ma-tii)","WordDisplayed":"si toti mortii ma-tii)","IdPhrase":"","Id":"33","IdFin":"","Type":0,"vectSolution":[{"Left":"și toți morții ma-tii).","Right":"și toți morții ma-tii)."}],"ExplicationSolution":"Închid paranteza.","EstSuggestion":false,"Vect_SolId":[],"IsUnknownProperNoun":false,"IsAnothA":false,"VectOtherResults":[]}},{"IndexPar":0,"LeftPos":840,"RightPos":853,"MotSolution":{"Start_Pos":840,"End_Pos":853,"WordSt":"Dupa cate vad","WordDisplayed":"Dupa cate vad","IdPhrase":"","Id":"34","IdFin":"","Type":0,"vectSolution":[{"Left":"După câte văd,","Right":"După câte văd,"}],"ExplicationSolution":"Adaug virgulă după cuvânt, conform regulilor de punctuație.","EstSuggestion":false,"Vect_SolId":[],"IsUnknownProperNoun":false,"IsAnothA":false,"VectOtherResults":[]}},{"IndexPar":0,"LeftPos":857,"RightPos":861,"MotSolution":{"Start_Pos":857,"End_Pos":861,"WordSt":"esti","WordDisplayed":"esti","IdPhrase":"","Id":"35","IdFin":"","Type":0,"vectSolution":[{"Left":"ești","Right":"ești"}],"ExplicationSolution":"Corectez lipsa diacritice.","EstSuggestion":false,"Vect_SolId":[],"IsUnknownProperNoun":false,"IsAnothA":false,"VectOtherResults":[]}},{"IndexPar":0,"LeftPos":869,"RightPos":893,"MotSolution":{"Start_Pos":869,"End_Pos":893,"WordSt":"copila...parinți tai nau","WordDisplayed":"copila...parinți tai nau","IdPhrase":"","Id":"36","IdFin":"","Type":0,"vectSolution":[{"Left":"copilă... părinții tăi n-au","Right":"copilă... părinții tăi n-au"}],"ExplicationSolution":"Corectez greșeli de ortografie (lipsă cratimă, \"n-au\" în loc de \"nau\") și corectez lipsa diacritice.","EstSuggestion":false,"Vect_SolId":[],"IsUnknownProperNoun":false,"IsAnothA":false,"VectOtherResults":[]}},{"IndexPar":0,"LeftPos":899,"RightPos":904,"MotSolution":{"Start_Pos":899,"End_Pos":904,"WordSt":"grija","WordDisplayed":"grija","IdPhrase":"","Id":"37","IdFin":"","Type":0,"vectSolution":[{"Left":"grijă","Right":"grijă"}],"ExplicationSolution":"Corectez lipsa diacritice.","EstSuggestion":false,"Vect_SolId":[],"IsUnknownProperNoun":false,"IsAnothA":false,"VectOtherResults":[]}},{"IndexPar":0,"LeftPos":913,"RightPos":917,"MotSolution":{"Start_Pos":913,"End_Pos":917,"WordSt":"cand","WordDisplayed":"cand","IdPhrase":"","Id":"38","IdFin":"","Type":0,"vectSolution":[{"Left":"când","Right":"când"}],"ExplicationSolution":"Corectez lipsa diacritice.","EstSuggestion":false,"Vect_SolId":[],"IsUnknownProperNoun":false,"IsAnothA":false,"VectOtherResults":[]}},{"IndexPar":0,"LeftPos":923,"RightPos":930,"MotSolution":{"Start_Pos":923,"End_Pos":930,"WordSt":"mika...","WordDisplayed":"mika...","IdPhrase":"","Id":"39","IdFin":"","Type":0,"vectSolution":[{"Left":"mică...","Right":"mică..."}],"ExplicationSolution":"Corectez greșeala de ortografie (lipsă cratimă) și înlocuiesc punctele cu puncte, conform contextului.","EstSuggestion":false,"Vect_SolId":[],"IsUnknownProperNoun":false,"IsAnothA":false,"VectOtherResults":[]}},{"IndexPar":0,"LeftPos":934,"RightPos":944,"MotSolution":{"Start_Pos":934,"End_Pos":944,"WordSt":"baga toata","WordDisplayed":"baga toata","IdPhrase":"","Id":"40","IdFin":"","Type":0,"vectSolution":[{"Left":"bagă toată","Right":"bagă toată"}],"ExplicationSolution":"Corectez lipsa diacritice.","EstSuggestion":false,"Vect_SolId":[],"IsUnknownProperNoun":false,"IsAnothA":false,"VectOtherResults":[]}},{"IndexPar":0,"LeftPos":953,"RightPos":964,"MotSolution":{"Start_Pos":953,"End_Pos":964,"WordSt":"produs...la","WordDisplayed":"produs...la","IdPhrase":"","Id":"41","IdFin":"","Type":0,"vectSolution":[{"Left":"produs... la","Right":"produs... la"}],"ExplicationSolution":"Elimin spațiul inutil între cuvinte.","EstSuggestion":false,"Vect_SolId":[],"IsUnknownProperNoun":false,"IsAnothA":false,"VectOtherResults":[]}},{"IndexPar":0,"LeftPos":973,"RightPos":977,"MotSolution":{"Start_Pos":973,"End_Pos":977,"WordSt":"pule","WordDisplayed":"pule","IdPhrase":"","Id":"42","IdFin":"","Type":0,"vectSolution":[{"Left":"pule,","Right":"pule,"}],"ExplicationSolution":"Adaug virgulă după cuvânt, conform regulilor de punctuație.","EstSuggestion":false,"Vect_SolId":[],"IsUnknownProperNoun":false,"IsAnothA":false,"VectOtherResults":[]}},{"IndexPar":0,"LeftPos":996,"RightPos":1012,"MotSolution":{"Start_Pos":996,"End_Pos":1012,"WordSt":"kur..etc...și in","WordDisplayed":"kur..etc...și in","IdPhrase":"","Id":"43","IdFin":"","Type":0,"vectSolution":[{"Left":"cur... etc... și în","Right":"cur... etc... și în"}],"ExplicationSolution":"Elimin spațiul inutil între cuvinte.","EstSuggestion":false,"Vect_SolId":[],"IsUnknownProperNoun":false,"IsAnothA":false,"VectOtherResults":[]}},{"IndexPar":0,"LeftPos":1030,"RightPos":1049,"MotSolution":{"Start_Pos":1030,"End_Pos":1049,"WordSt":"traseista retardata","WordDisplayed":"traseista retardata","IdPhrase":"","Id":"44","IdFin":"","Type":0,"vectSolution":[{"Left":"traseistă retardată.","Right":"traseistă retardată."}],"ExplicationSolution":"Adaug punct la finalul frazei.","EstSuggestion":false,"Vect_SolId":[],"IsUnknownProperNoun":false,"IsAnothA":false,"VectOtherResults":[]}},{"IndexPar":0,"LeftPos":1051,"RightPos":1064,"MotSolution":{"Start_Pos":1051,"End_Pos":1064,"WordSt":"Bah bagami-as","WordDisplayed":"Bah bagami-as","IdPhrase":"","Id":"45","IdFin":"","Type":0,"vectSolution":[{"Left":"Bă, bagă-mi-aș","Right":"Bă, bagă-mi-aș"}],"ExplicationSolution":"Corectez exprimarea.","EstSuggestion":false,"Vect_SolId":[],"IsUnknownProperNoun":false,"IsAnothA":false,"VectOtherResults":[]}},{"IndexPar":0,"LeftPos":1070,"RightPos":1076,"MotSolution":{"Start_Pos":1070,"End_Pos":1076,"WordSt":"in ala","WordDisplayed":"in ala","IdPhrase":"","Id":"46","IdFin":"","Type":0,"vectSolution":[{"Left":"în ăla","Right":"în ăla"}],"ExplicationSolution":"Corectez exprimarea.","EstSuggestion":false,"Vect_SolId":[],"IsUnknownProperNoun":false,"IsAnothA":false,"VectOtherResults":[]}},{"IndexPar":0,"LeftPos":1086,"RightPos":1100,"MotSolution":{"Start_Pos":1086,"End_Pos":1100,"WordSt":"pisat in raul,","WordDisplayed":"pisat in raul,","IdPhrase":"","Id":"47","IdFin":"","Type":0,"vectSolution":[{"Left":"pișat în râul,","Right":"pișat în râul,"}],"ExplicationSolution":"Corectez exprimarea.","EstSuggestion":false,"Vect_SolId":[],"IsUnknownProperNoun":false,"IsAnothA":false,"VectOtherResults":[]}},{"IndexPar":0,"LeftPos":1110,"RightPos":1119,"MotSolution":{"Start_Pos":1110,"End_Pos":1119,"WordSt":"varsat in","WordDisplayed":"varsat in","IdPhrase":"","Id":"48","IdFin":"","Type":0,"vectSolution":[{"Left":"vărsat în","Right":"vărsat în"}],"ExplicationSolution":"Corectez exprimarea.","EstSuggestion":false,"Vect_SolId":[],"IsUnknownProperNoun":false,"IsAnothA":false,"VectOtherResults":[]}},{"IndexPar":0,"LeftPos":1129,"RightPos":1134,"MotSolution":{"Start_Pos":1129,"End_Pos":1134,"WordSt":"langa","WordDisplayed":"langa","IdPhrase":"","Id":"49","IdFin":"","Type":0,"vectSolution":[{"Left":"lângă","Right":"lângă"}],"ExplicationSolution":"Corectez exprimarea.","EstSuggestion":false,"Vect_SolId":[],"IsUnknownProperNoun":false,"IsAnothA":false,"VectOtherResults":[]}},{"IndexPar":0,"LeftPos":1224,"RightPos":1232,"MotSolution":{"Start_Pos":1224,"End_Pos":1232,"WordSt":"pamantul","WordDisplayed":"pamantul","IdPhrase":"","Id":"50","IdFin":"","Type":0,"vectSolution":[{"Left":"pământul","Right":"pământul"}],"ExplicationSolution":"Corectez lipsa diacritice.","EstSuggestion":false,"Vect_SolId":[],"IsUnknownProperNoun":false,"IsAnothA":false,"VectOtherResults":[]}},{"IndexPar":0,"LeftPos":1245,"RightPos":1261,"MotSolution":{"Start_Pos":1245,"End_Pos":1261,"WordSt":"plantata samanta","WordDisplayed":"plantata samanta","IdPhrase":"","Id":"51","IdFin":"","Type":0,"vectSolution":[{"Left":"plantată sămânța","Right":"plantată sămânța"}],"ExplicationSolution":"Corectez exprimarea.","EstSuggestion":false,"Vect_SolId":[],"IsUnknownProperNoun":false,"IsAnothA":false,"VectOtherResults":[]}},{"IndexPar":0,"LeftPos":1302,"RightPos":1317,"MotSolution":{"Start_Pos":1302,"End_Pos":1317,"WordSt":"facut tamplarul","WordDisplayed":"facut tamplarul","IdPhrase":"","Id":"52","IdFin":"","Type":0,"vectSolution":[{"Left":"făcut tâmplarul","Right":"făcut tâmplarul"}],"ExplicationSolution":"Corectez exprimarea.","EstSuggestion":false,"Vect_SolId":[],"IsUnknownProperNoun":false,"IsAnothA":false,"VectOtherResults":[]}},{"IndexPar":0,"LeftPos":1327,"RightPos":1329,"MotSolution":{"Start_Pos":1327,"End_Pos":1329,"WordSt":"in","WordDisplayed":"in","IdPhrase":"","Id":"53","IdFin":"","Type":0,"vectSolution":[{"Left":"în","Right":"în"}],"ExplicationSolution":"Corectez exprimarea.","EstSuggestion":false,"Vect_SolId":[],"IsUnknownProperNoun":false,"IsAnothA":false,"VectOtherResults":[]}},{"IndexPar":0,"LeftPos":1353,"RightPos":1363,"MotSolution":{"Start_Pos":1353,"End_Pos":1363,"WordSt":"ala gaurit","WordDisplayed":"ala gaurit","IdPhrase":"","Id":"54","IdFin":"","Type":0,"vectSolution":[{"Left":"ăla găurit","Right":"ăla găurit"}],"ExplicationSolution":"Corectez exprimarea.","EstSuggestion":false,"Vect_SolId":[],"IsUnknownProperNoun":false,"IsAnothA":false,"VectOtherResults":[]}},{"IndexPar":0,"LeftPos":1379,"RightPos":1386,"MotSolution":{"Start_Pos":1379,"End_Pos":1386,"WordSt":"mata in","WordDisplayed":"mata in","IdPhrase":"","Id":"55","IdFin":"","Type":0,"vectSolution":[{"Left":"ma-ta în","Right":"ma-ta în"}],"ExplicationSolution":"Corectez exprimarea.","EstSuggestion":false,"Vect_SolId":[],"IsUnknownProperNoun":false,"IsAnothA":false,"VectOtherResults":[]}},{"IndexPar":0,"LeftPos":1395,"RightPos":1399,"MotSolution":{"Start_Pos":1395,"End_Pos":1399,"WordSt":"cand","WordDisplayed":"cand","IdPhrase":"","Id":"56","IdFin":"","Type":0,"vectSolution":[{"Left":"când","Right":"când"}],"ExplicationSolution":"Corectez exprimarea.","EstSuggestion":false,"Vect_SolId":[],"IsUnknownProperNoun":false,"IsAnothA":false,"VectOtherResults":[]}},{"IndexPar":0,"LeftPos":1413,"RightPos":1418,"MotSolution":{"Start_Pos":1413,"End_Pos":1418,"WordSt":"tactu","WordDisplayed":"tactu","IdPhrase":"","Id":"57","IdFin":"","Type":0,"vectSolution":[{"Left":"tac-tu.","Right":"tac-tu."}],"ExplicationSolution":"Corectez exprimarea.","EstSuggestion":false,"Vect_SolId":[],"IsUnknownProperNoun":false,"IsAnothA":false,"VectOtherResults":[]}},{"IndexPar":0,"LeftPos":1420,"RightPos":1423,"MotSolution":{"Start_Pos":1420,"End_Pos":1423,"WordSt":"Ba,","WordDisplayed":"Ba,","IdPhrase":"","Id":"58","IdFin":"","Type":0,"vectSolution":[{"Left":"Bă,","Right":"Bă,"}],"ExplicationSolution":"Adaug virgulă după cuvânt, conform regulilor de punctuație.","EstSuggestion":false,"Vect_SolId":[],"IsUnknownProperNoun":false,"IsAnothA":false,"VectOtherResults":[]}},{"IndexPar":0,"LeftPos":1429,"RightPos":1431,"MotSolution":{"Start_Pos":1429,"End_Pos":1431,"WordSt":"ca","WordDisplayed":"ca","IdPhrase":"","Id":"59","IdFin":"","Type":0,"vectSolution":[{"Left":"că","Right":"că"}],"ExplicationSolution":"Corectez lipsa diacritice.","EstSuggestion":false,"Vect_SolId":[],"IsUnknownProperNoun":false,"IsAnothA":false,"VectOtherResults":[]}},{"IndexPar":0,"LeftPos":1435,"RightPos":1439,"MotSolution":{"Start_Pos":1435,"End_Pos":1439,"WordSt":"esti","WordDisplayed":"esti","IdPhrase":"","Id":"60","IdFin":"","Type":0,"vectSolution":[{"Left":"ești","Right":"ești"}],"ExplicationSolution":"Corectez lipsa diacritice.","EstSuggestion":false,"Vect_SolId":[],"IsUnknownProperNoun":false,"IsAnothA":false,"VectOtherResults":[]}},{"IndexPar":0,"LeftPos":1463,"RightPos":1472,"MotSolution":{"Start_Pos":1463,"End_Pos":1472,"WordSt":"reusit sa","WordDisplayed":"reusit sa","IdPhrase":"","Id":"61","IdFin":"","Type":0,"vectSolution":[{"Left":"reușit să","Right":"reușit să"}],"ExplicationSolution":"Corectez exprimarea.","EstSuggestion":false,"Vect_SolId":[],"IsUnknownProperNoun":false,"IsAnothA":false,"VectOtherResults":[]}},{"IndexPar":0,"LeftPos":1482,"RightPos":1505,"MotSolution":{"Start_Pos":1482,"End_Pos":1505,"WordSt":"prezrvativu lu tacto in","WordDisplayed":"prezrvativu lu tacto in","IdPhrase":"","Id":"62","IdFin":"","Type":0,"vectSolution":[{"Left":"prezervativul lui tac-tu în","Right":"prezervativul lui tac-tu în"}],"ExplicationSolution":"Corectez exprimarea.","EstSuggestion":false,"Vect_SolId":[],"IsUnknownProperNoun":false,"IsAnothA":false,"VectOtherResults":[]}},{"IndexPar":0,"LeftPos":1512,"RightPos":1533,"MotSolution":{"Start_Pos":1512,"End_Pos":1533,"WordSt":"ma-tii, deserta-mi-as","WordDisplayed":"ma-tii, deserta-mi-as","IdPhrase":"","Id":"63","IdFin":"","Type":0,"vectSolution":[{"Left":"ma-tii. Deșerta-mi-aș","Right":"ma-tii. Deșerta-mi-aș"}],"ExplicationSolution":"Corectez exprimarea.","EstSuggestion":false,"Vect_SolId":[],"IsUnknownProperNoun":false,"IsAnothA":false,"VectOtherResults":[]}},{"IndexPar":0,"LeftPos":1542,"RightPos":1549,"MotSolution":{"Start_Pos":1542,"End_Pos":1549,"WordSt":"in gitu","WordDisplayed":"in gitu","IdPhrase":"","Id":"64","IdFin":"","Type":0,"vectSolution":[{"Left":"în gâtul","Right":"în gâtul"}],"ExplicationSolution":"Corectez exprimarea.","EstSuggestion":false,"Vect_SolId":[],"IsUnknownProperNoun":false,"IsAnothA":false,"VectOtherResults":[]}},{"IndexPar":0,"LeftPos":1559,"RightPos":1561,"MotSolution":{"Start_Pos":1559,"End_Pos":1561,"WordSt":"Sa","WordDisplayed":"Sa","IdPhrase":"","Id":"65","IdFin":"","Type":0,"vectSolution":[{"Left":"Să","Right":"Să"}],"ExplicationSolution":"Corectez lipsa diacritice.","EstSuggestion":false,"Vect_SolId":[],"IsUnknownProperNoun":false,"IsAnothA":false,"VectOtherResults":[]}},{"IndexPar":0,"LeftPos":1569,"RightPos":1576,"MotSolution":{"Start_Pos":1569,"End_Pos":1576,"WordSt":"pina ti","WordDisplayed":"pina ti","IdPhrase":"","Id":"66","IdFin":"","Type":0,"vectSolution":[{"Left":"până ți","Right":"până ți"}],"ExplicationSolution":"Corectez exprimarea.","EstSuggestion":false,"Vect_SolId":[],"IsUnknownProperNoun":false,"IsAnothA":false,"VectOtherResults":[]}},{"IndexPar":0,"LeftPos":1591,"RightPos":1598,"MotSolution":{"Start_Pos":1591,"End_Pos":1598,"WordSt":"dintii,","WordDisplayed":"dintii,","IdPhrase":"","Id":"67","IdFin":"","Type":0,"vectSolution":[{"Left":"dinții,","Right":"dinții,"}],"ExplicationSolution":"Corectez exprimarea.","EstSuggestion":false,"Vect_SolId":[],"IsUnknownProperNoun":false,"IsAnothA":false,"VectOtherResults":[]}},{"IndexPar":0,"LeftPos":1622,"RightPos":1629,"MotSolution":{"Start_Pos":1622,"End_Pos":1629,"WordSt":"rind ca","WordDisplayed":"rind ca","IdPhrase":"","Id":"68","IdFin":"","Type":0,"vectSolution":[{"Left":"rând, că","Right":"rând, că"}],"ExplicationSolution":"Corectez exprimarea.","EstSuggestion":false,"Vect_SolId":[],"IsUnknownProperNoun":false,"IsAnothA":false,"VectOtherResults":[]}},{"IndexPar":0,"LeftPos":1633,"RightPos":1637,"MotSolution":{"Start_Pos":1633,"End_Pos":1637,"WordSt":"sint","WordDisplayed":"sint","IdPhrase":"","Id":"69","IdFin":"","Type":0,"vectSolution":[{"Left":"sunt","Right":"sunt"}],"ExplicationSolution":"Corectez exprimarea.","EstSuggestion":false,"Vect_SolId":[],"IsUnknownProperNoun":false,"IsAnothA":false,"VectOtherResults":[]}},{"IndexPar":0,"LeftPos":1649,"RightPos":1661,"MotSolution":{"Start_Pos":1649,"End_Pos":1661,"WordSt":"sloboz, o sa","WordDisplayed":"sloboz, o sa","IdPhrase":"","Id":"70","IdFin":"","Type":0,"vectSolution":[{"Left":"sloboz. O să","Right":"sloboz. O să"}],"ExplicationSolution":"Corectez exprimarea.","EstSuggestion":false,"Vect_SolId":[],"IsUnknownProperNoun":false,"IsAnothA":false,"VectOtherResults":[]}},{"IndexPar":0,"LeftPos":1680,"RightPos":1688,"MotSolution":{"Start_Pos":1680,"End_Pos":1688,"WordSt":"neamu lu","WordDisplayed":"neamu lu","IdPhrase":"","Id":"71","IdFin":"","Type":0,"vectSolution":[{"Left":"neamul lui","Right":"neamul lui"}],"ExplicationSolution":"Corectez exprimarea.","EstSuggestion":false,"Vect_SolId":[],"IsUnknownProperNoun":false,"IsAnothA":false,"VectOtherResults":[]}},{"IndexPar":0,"LeftPos":1702,"RightPos":1717,"MotSolution":{"Start_Pos":1702,"End_Pos":1717,"WordSt":"sa va saturati!","WordDisplayed":"sa va saturati!","IdPhrase":"","Id":"72","IdFin":"","Type":0,"vectSolution":[{"Left":"să vă săturați!","Right":"să vă săturați!"}],"ExplicationSolution":"Corectez exprimarea.","EstSuggestion":false,"Vect_SolId":[],"IsUnknownProperNoun":false,"IsAnothA":false,"VectOtherResults":[]}},{"IndexPar":0,"LeftPos":1719,"RightPos":1726,"MotSolution":{"Start_Pos":1719,"End_Pos":1726,"WordSt":"Fraiera","WordDisplayed":"Fraiera","IdPhrase":"","Id":"73","IdFin":"","Type":0,"vectSolution":[{"Left":"Fraieră","Right":"Fraieră"}],"ExplicationSolution":"Corectez exprimarea.","EstSuggestion":false,"Vect_SolId":[],"IsUnknownProperNoun":false,"IsAnothA":false,"VectOtherResults":[]}},{"IndexPar":0,"LeftPos":1740,"RightPos":1744,"MotSolution":{"Start_Pos":1740,"End_Pos":1744,"WordSt":"cind","WordDisplayed":"cind","IdPhrase":"","Id":"74","IdFin":"","Type":0,"vectSolution":[{"Left":"când","Right":"când"}],"ExplicationSolution":"Corectez exprimarea.","EstSuggestion":false,"Vect_SolId":[],"IsUnknownProperNoun":false,"IsAnothA":false,"VectOtherResults":[]}},{"IndexPar":0,"LeftPos":1749,"RightPos":1757,"MotSolution":{"Start_Pos":1749,"End_Pos":1757,"WordSt":"cracanat","WordDisplayed":"cracanat","IdPhrase":"","Id":"75","IdFin":"","Type":0,"vectSolution":[{"Left":"crăcănat","Right":"crăcănat"}],"ExplicationSolution":"Corectez exprimarea.","EstSuggestion":false,"Vect_SolId":[],"IsUnknownProperNoun":false,"IsAnothA":false,"VectOtherResults":[]}},{"IndexPar":0,"LeftPos":1761,"RightPos":1769,"MotSolution":{"Start_Pos":1761,"End_Pos":1769,"WordSt":"tacto si","WordDisplayed":"tacto si","IdPhrase":"","Id":"76","IdFin":"","Type":0,"vectSolution":[{"Left":"tac-tu și","Right":"tac-tu și"}],"ExplicationSolution":"Corectez exprimarea.","EstSuggestion":false,"Vect_SolId":[],"IsUnknownProperNoun":false,"IsAnothA":false,"VectOtherResults":[]}},{"IndexPar":0,"LeftPos":1775,"RightPos":1783,"MotSolution":{"Start_Pos":1775,"End_Pos":1783,"WordSt":"spircait","WordDisplayed":"spircait","IdPhrase":"","Id":"77","IdFin":"","Type":0,"vectSolution":[{"Left":"spircuit","Right":"spircuit"}],"ExplicationSolution":"Corectez exprimarea.","EstSuggestion":false,"Vect_SolId":[],"IsUnknownProperNoun":false,"IsAnothA":false,"VectOtherResults":[]}},{"IndexPar":0,"LeftPos":1793,"RightPos":1803,"MotSolution":{"Start_Pos":1793,"End_Pos":1803,"WordSt":"amaritule!","WordDisplayed":"amaritule!","IdPhrase":"","Id":"78","IdFin":"","Type":0,"vectSolution":[{"Left":"amărâtule!","Right":"amărâtule!"}],"ExplicationSolution":"Corectez exprimarea.","EstSuggestion":false,"Vect_SolId":[],"IsUnknownProperNoun":false,"IsAnothA":false,"VectOtherResults":[]}},{"IndexPar":0,"LeftPos":1805,"RightPos":1815,"MotSolution":{"Start_Pos":1805,"End_Pos":1815,"WordSt":"Sscaciunea","WordDisplayed":"Sscaciunea","IdPhrase":"","Id":"79","IdFin":"","Type":0,"vectSolution":[{"Left":"Scârboșenia","Right":"Scârboșenia"}],"ExplicationSolution":"Corectez exprimarea.","EstSuggestion":false,"Vect_SolId":[],"IsUnknownProperNoun":false,"IsAnothA":false,"VectOtherResults":[]}},{"IndexPar":0,"LeftPos":1831,"RightPos":1833,"MotSolution":{"Start_Pos":1831,"End_Pos":1833,"WordSt":"ma","WordDisplayed":"ma","IdPhrase":"","Id":"80","IdFin":"","Type":0,"vectSolution":[{"Left":"mă","Right":"mă"}],"ExplicationSolution":"Corectez exprimarea.","EstSuggestion":false,"Vect_SolId":[],"IsUnknownProperNoun":false,"IsAnothA":false,"VectOtherResults":[]}},{"IndexPar":0,"LeftPos":1850,"RightPos":1863,"MotSolution":{"Start_Pos":1850,"End_Pos":1863,"WordSt":"si ma gindesc","WordDisplayed":"si ma gindesc","IdPhrase":"","Id":"81","IdFin":"","Type":0,"vectSolution":[{"Left":"și mă gândesc","Right":"și mă gândesc"}],"ExplicationSolution":"Corectez exprimarea.","EstSuggestion":false,"Vect_SolId":[],"IsUnknownProperNoun":false,"IsAnothA":false,"VectOtherResults":[]}},{"IndexPar":0,"LeftPos":1875,"RightPos":1882,"MotSolution":{"Start_Pos":1875,"End_Pos":1882,"WordSt":"dentara","WordDisplayed":"dentara","IdPhrase":"","Id":"82","IdFin":"","Type":0,"vectSolution":[{"Left":"dentară","Right":"dentară"}],"ExplicationSolution":"Corectez exprimarea.","EstSuggestion":false,"Vect_SolId":[],"IsUnknownProperNoun":false,"IsAnothA":false,"VectOtherResults":[]}},{"IndexPar":0,"LeftPos":1885,"RightPos":1911,"MotSolution":{"Start_Pos":1885,"End_Pos":1911,"WordSt":"lu ma-ta, ma excita gindul","WordDisplayed":"lu ma-ta, ma excita gindul","IdPhrase":"","Id":"83","IdFin":"","Type":0,"vectSolution":[{"Left":"lui ma-ta. Mă excită gândul","Right":"lui ma-ta. Mă excită gândul"}],"ExplicationSolution":"Corectez exprimarea.","EstSuggestion":false,"Vect_SolId":[],"IsUnknownProperNoun":false,"IsAnothA":false,"VectOtherResults":[]}},{"IndexPar":0,"LeftPos":1921,"RightPos":1925,"MotSolution":{"Start_Pos":1921,"End_Pos":1925,"WordSt":"cind","WordDisplayed":"cind","IdPhrase":"","Id":"84","IdFin":"","Type":0,"vectSolution":[{"Left":"când","Right":"când"}],"ExplicationSolution":"Corectez exprimarea.","EstSuggestion":false,"Vect_SolId":[],"IsUnknownProperNoun":false,"IsAnothA":false,"VectOtherResults":[]}},{"IndexPar":0,"LeftPos":1940,"RightPos":1960,"MotSolution":{"Start_Pos":1940,"End_Pos":1960,"WordSt":"si tacto a-ti scapat","WordDisplayed":"si tacto a-ti scapat","IdPhrase":"","Id":"85","IdFin":"","Type":0,"vectSolution":[{"Left":"și tac-tu ați scăpat","Right":"și tac-tu ați scăpat"}],"ExplicationSolution":"Corectez exprimarea.","EstSuggestion":false,"Vect_SolId":[],"IsUnknownProperNoun":false,"IsAnothA":false,"VectOtherResults":[]}},{"IndexPar":0,"LeftPos":1964,"RightPos":1987,"MotSolution":{"Start_Pos":1964,"End_Pos":1987,"WordSt":"labute si a-ti iesit in","WordDisplayed":"labute si a-ti iesit in","IdPhrase":"","Id":"86","IdFin":"","Type":0,"vectSolution":[{"Left":"lăbuțe și ați ieșit în","Right":"lăbuțe și ați ieșit în"}],"ExplicationSolution":"Corectez exprimarea.","EstSuggestion":false,"Vect_SolId":[],"IsUnknownProperNoun":false,"IsAnothA":false,"VectOtherResults":[]}},{"IndexPar":0,"LeftPos":1993,"RightPos":2013,"MotSolution":{"Start_Pos":1993,"End_Pos":2013,"WordSt":"iepurasi ? Vedeti ca","WordDisplayed":"iepurasi ? Vedeti ca","IdPhrase":"","Id":"87","IdFin":"","Type":0,"vectSolution":[{"Left":"iepurași? Vedeți că","Right":"iepurași? Vedeți că"}],"ExplicationSolution":"Corectez exprimarea.","EstSuggestion":false,"Vect_SolId":[],"IsUnknownProperNoun":false,"IsAnothA":false,"VectOtherResults":[]}},{"IndexPar":0,"LeftPos":2022,"RightPos":2042,"MotSolution":{"Start_Pos":2022,"End_Pos":2042,"WordSt":"perversa si .....vai","WordDisplayed":"perversa si .....vai","IdPhrase":"","Id":"88","IdFin":"","Type":0,"vectSolution":[{"Left":"perversă și... vai","Right":"perversă și... vai"}],"ExplicationSolution":"Corectez exprimarea.","EstSuggestion":false,"Vect_SolId":[],"IsUnknownProperNoun":false,"IsAnothA":false,"VectOtherResults":[]}},{"IndexPar":0,"LeftPos":2051,"RightPos":2086,"MotSolution":{"Start_Pos":2051,"End_Pos":2086,"WordSt":"voastra! Pregatiti magiunu ca aveti","WordDisplayed":"voastra! Pregatiti magiunu ca aveti","IdPhrase":"","Id":"89","IdFin":"","Type":0,"vectSolution":[{"Left":"voastră! Pregătiți magiunul că aveți","Right":"voastră! Pregătiți magiunul că aveți"}],"ExplicationSolution":"Corectez exprimarea.","EstSuggestion":false,"Vect_SolId":[],"IsUnknownProperNoun":false,"IsAnothA":false,"VectOtherResults":[]}},{"IndexPar":0,"LeftPos":2092,"RightPos":2100,"MotSolution":{"Start_Pos":2092,"End_Pos":2100,"WordSt":"acasa(in","WordDisplayed":"acasa(in","IdPhrase":"","Id":"90","IdFin":"","Type":0,"vectSolution":[{"Left":"acasă (în","Right":"acasă (în"}],"ExplicationSolution":"Corectez exprimarea.","EstSuggestion":false,"Vect_SolId":[],"IsUnknownProperNoun":false,"IsAnothA":false,"VectOtherResults":[]}},{"IndexPar":0,"LeftPos":2108,"RightPos":2128,"MotSolution":{"Start_Pos":2108,"End_Pos":2128,"WordSt":"alifie ca altceva ?)","WordDisplayed":"alifie ca altceva ?)","IdPhrase":"","Id":"91","IdFin":"","Type":0,"vectSolution":[{"Left":"alifie, că altceva?).","Right":"alifie, că altceva?)."}],"ExplicationSolution":"Corectez exprimarea.","EstSuggestion":false,"Vect_SolId":[],"IsUnknownProperNoun":false,"IsAnothA":false,"VectOtherResults":[]}},{"IndexPar":0,"LeftPos":2130,"RightPos":2135,"MotSolution":{"Start_Pos":2130,"End_Pos":2135,"WordSt":"Spune","WordDisplayed":"Spune","IdPhrase":"","Id":"92","IdFin":"","Type":0,"vectSolution":[{"Left":"Spune,","Right":"Spune,"}],"ExplicationSolution":"Corectez exprimarea.","EstSuggestion":false,"Vect_SolId":[],"IsUnknownProperNoun":false,"IsAnothA":false,"VectOtherResults":[]}},{"IndexPar":0,"LeftPos":2148,"RightPos":2153,"MotSolution":{"Start_Pos":2148,"End_Pos":2153,"WordSt":"facut","WordDisplayed":"facut","IdPhrase":"","Id":"93","IdFin":"","Type":0,"vectSolution":[{"Left":"făcut","Right":"făcut"}],"ExplicationSolution":"Corectez exprimarea.","EstSuggestion":false,"Vect_SolId":[],"IsUnknownProperNoun":false,"IsAnothA":false,"VectOtherResults":[]}},{"IndexPar":0,"LeftPos":2177,"RightPos":2188,"MotSolution":{"Start_Pos":2177,"End_Pos":2188,"WordSt":"in gradina?","WordDisplayed":"in gradina?","IdPhrase":"","Id":"94","IdFin":"","Type":0,"vectSolution":[{"Left":"în grădină?","Right":"în grădină?"}],"ExplicationSolution":"Corectez exprimarea.","EstSuggestion":false,"Vect_SolId":[],"IsUnknownProperNoun":false,"IsAnothA":false,"VectOtherResults":[]}},{"IndexPar":0,"LeftPos":2191,"RightPos":2204,"MotSolution":{"Start_Pos":2191,"End_Pos":2204,"WordSt":"fericita daca","WordDisplayed":"fericita daca","IdPhrase":"","Id":"95","IdFin":"","Type":0,"vectSolution":[{"Left":"fericită dacă","Right":"fericită dacă"}],"ExplicationSolution":"Corectez exprimarea.","EstSuggestion":false,"Vect_SolId":[],"IsUnknownProperNoun":false,"IsAnothA":false,"VectOtherResults":[]}},{"IndexPar":0,"LeftPos":2207,"RightPos":2210,"MotSolution":{"Start_Pos":2207,"End_Pos":2210,"WordSt":"asa","WordDisplayed":"asa","IdPhrase":"","Id":"96","IdFin":"","Type":0,"vectSolution":[{"Left":"așa","Right":"așa"}],"ExplicationSolution":"Corectez exprimarea.","EstSuggestion":false,"Vect_SolId":[],"IsUnknownProperNoun":false,"IsAnothA":false,"VectOtherResults":[]}},{"IndexPar":0,"LeftPos":2242,"RightPos":2252,"MotSolution":{"Start_Pos":2242,"End_Pos":2252,"WordSt":"satenii lu","WordDisplayed":"satenii lu","IdPhrase":"","Id":"97","IdFin":"","Type":0,"vectSolution":[{"Left":"sătenii lui","Right":"sătenii lui"}],"ExplicationSolution":"Corectez exprimarea.","EstSuggestion":false,"Vect_SolId":[],"IsUnknownProperNoun":false,"IsAnothA":false,"VectOtherResults":[]}},{"IndexPar":0,"LeftPos":2259,"RightPos":2263,"MotSolution":{"Start_Pos":2259,"End_Pos":2263,"WordSt":"cind","WordDisplayed":"cind","IdPhrase":"","Id":"98","IdFin":"","Type":0,"vectSolution":[{"Left":"când","Right":"când"}],"ExplicationSolution":"Corectez exprimarea.","EstSuggestion":false,"Vect_SolId":[],"IsUnknownProperNoun":false,"IsAnothA":false,"VectOtherResults":[]}},{"IndexPar":0,"LeftPos":2266,"RightPos":2271,"MotSolution":{"Start_Pos":2266,"End_Pos":2271,"WordSt":"tacto","WordDisplayed":"tacto","IdPhrase":"","Id":"99","IdFin":"","Type":0,"vectSolution":[{"Left":"tac-tu","Right":"tac-tu"}],"ExplicationSolution":"Corectez exprimarea.","EstSuggestion":false,"Vect_SolId":[],"IsUnknownProperNoun":false,"IsAnothA":false,"VectOtherResults":[]}},{"IndexPar":0,"LeftPos":2275,"RightPos":2283,"MotSolution":{"Start_Pos":2275,"End_Pos":2283,"WordSt":"tractoru","WordDisplayed":"tractoru","IdPhrase":"","Id":"100","IdFin":"","Type":0,"vectSolution":[{"Left":"tractorul","Right":"tractorul"}],"ExplicationSolution":"Corectez exprimarea.","EstSuggestion":false,"Vect_SolId":[],"IsUnknownProperNoun":false,"IsAnothA":false,"VectOtherResults":[]}},{"IndexPar":0,"LeftPos":2293,"RightPos":2305,"MotSolution":{"Start_Pos":2293,"End_Pos":2305,"WordSt":"Erecta-mi-as","WordDisplayed":"Erecta-mi-as","IdPhrase":"","Id":"101","IdFin":"","Type":0,"vectSolution":[{"Left":"Erecta-mi-aș","Right":"Erecta-mi-aș"}],"ExplicationSolution":"Corectez exprimarea.","EstSuggestion":false,"Vect_SolId":[],"IsUnknownProperNoun":false,"IsAnothA":false,"VectOtherResults":[]}},{"IndexPar":0,"LeftPos":2311,"RightPos":2321,"MotSolution":{"Start_Pos":2311,"End_Pos":2321,"WordSt":"in esofagu","WordDisplayed":"in esofagu","IdPhrase":"","Id":"102","IdFin":"","Type":0,"vectSolution":[{"Left":"în esofagul","Right":"în esofagul"}],"ExplicationSolution":"Corectez exprimarea.","EstSuggestion":false,"Vect_SolId":[],"IsUnknownProperNoun":false,"IsAnothA":false,"VectOtherResults":[]}},{"IndexPar":0,"LeftPos":2331,"RightPos":2333,"MotSolution":{"Start_Pos":2331,"End_Pos":2333,"WordSt":"Sa","WordDisplayed":"Sa","IdPhrase":"","Id":"103","IdFin":"","Type":0,"vectSolution":[{"Left":"Să","Right":"Să"}],"ExplicationSolution":"Corectez exprimarea.","EstSuggestion":false,"Vect_SolId":[],"IsUnknownProperNoun":false,"IsAnothA":false,"VectOtherResults":[]}},{"IndexPar":0,"LeftPos":2343,"RightPos":2347,"MotSolution":{"Start_Pos":2343,"End_Pos":2347,"WordSt":"gitu","WordDisplayed":"gitu","IdPhrase":"","Id":"104","IdFin":"","Type":0,"vectSolution":[{"Left":"gâtul","Right":"gâtul"}],"ExplicationSolution":"Corectez exprimarea.","EstSuggestion":false,"Vect_SolId":[],"IsUnknownProperNoun":false,"IsAnothA":false,"VectOtherResults":[]}},{"IndexPar":0,"LeftPos":2358,"RightPos":2365,"MotSolution":{"Start_Pos":2358,"End_Pos":2365,"WordSt":"slobozu","WordDisplayed":"slobozu","IdPhrase":"","Id":"105","IdFin":"","Type":0,"vectSolution":[{"Left":"slobozul","Right":"slobozul"}],"ExplicationSolution":"Corectez exprimarea.","EstSuggestion":false,"Vect_SolId":[],"IsUnknownProperNoun":false,"IsAnothA":false,"VectOtherResults":[]}},{"IndexPar":0,"LeftPos":2370,"RightPos":2379,"MotSolution":{"Start_Pos":2370,"End_Pos":2379,"WordSt":"tataie ca","WordDisplayed":"tataie ca","IdPhrase":"","Id":"106","IdFin":"","Type":0,"vectSolution":[{"Left":"tataie, că","Right":"tataie, că"}],"ExplicationSolution":"Corectez exprimarea.","EstSuggestion":false,"Vect_SolId":[],"IsUnknownProperNoun":false,"IsAnothA":false,"VectOtherResults":[]}},{"IndexPar":0,"LeftPos":2397,"RightPos":2403,"MotSolution":{"Start_Pos":2397,"End_Pos":2403,"WordSt":"satura","WordDisplayed":"satura","IdPhrase":"","Id":"107","IdFin":"","Type":0,"vectSolution":[{"Left":"satură","Right":"satură"}],"ExplicationSolution":"Corectez exprimarea.","EstSuggestion":false,"Vect_SolId":[],"IsUnknownProperNoun":false,"IsAnothA":false,"VectOtherResults":[]}},{"IndexPar":0,"LeftPos":2407,"RightPos":2416,"MotSolution":{"Start_Pos":2407,"End_Pos":2416,"WordSt":"vestejita","WordDisplayed":"vestejita","IdPhrase":"","Id":"108","IdFin":"","Type":0,"vectSolution":[{"Left":"veștejita","Right":"veștejita"}],"ExplicationSolution":"Corectez exprimarea.","EstSuggestion":false,"Vect_SolId":[],"IsUnknownProperNoun":false,"IsAnothA":false,"VectOtherResults":[]}},{"IndexPar":0,"LeftPos":2436,"RightPos":2453,"MotSolution":{"Start_Pos":2436,"End_Pos":2453,"WordSt":"laba puturoasa in","WordDisplayed":"laba puturoasa in","IdPhrase":"","Id":"109","IdFin":"","Type":0,"vectSolution":[{"Left":"labă puturoasă în","Right":"labă puturoasă în"}],"ExplicationSolution":"Corectez exprimarea.","EstSuggestion":false,"Vect_SolId":[],"IsUnknownProperNoun":false,"IsAnothA":false,"VectOtherResults":[]}},{"IndexPar":0,"LeftPos":2475,"RightPos":2477,"MotSolution":{"Start_Pos":2475,"End_Pos":2477,"WordSt":"ca","WordDisplayed":"ca","IdPhrase":"","Id":"110","IdFin":"","Type":0,"vectSolution":[{"Left":"că","Right":"că"}],"ExplicationSolution":"Corectez exprimarea.","EstSuggestion":false,"Vect_SolId":[],"IsUnknownProperNoun":false,"IsAnothA":false,"VectOtherResults":[]}},{"IndexPar":0,"LeftPos":2502,"RightPos":2507,"MotSolution":{"Start_Pos":2502,"End_Pos":2507,"WordSt":"De ar","WordDisplayed":"De ar","IdPhrase":"","Id":"111","IdFin":"","Type":0,"vectSolution":[{"Left":"De-ar","Right":"De-ar"}],"ExplicationSolution":"Corectez exprimarea.","EstSuggestion":false,"Vect_SolId":[],"IsUnknownProperNoun":false,"IsAnothA":false,"VectOtherResults":[]}},{"IndexPar":0,"LeftPos":2522,"RightPos":2531,"MotSolution":{"Start_Pos":2522,"End_Pos":2531,"WordSt":"pa Dunare","WordDisplayed":"pa Dunare","IdPhrase":"","Id":"112","IdFin":"","Type":0,"vectSolution":[{"Left":"pe Dunăre,","Right":"pe Dunăre,"}],"ExplicationSolution":"Corectez exprimarea.","EstSuggestion":false,"Vect_SolId":[],"IsUnknownProperNoun":false,"IsAnothA":false,"VectOtherResults":[]}},{"IndexPar":0,"LeftPos":2541,"RightPos":2551,"MotSolution":{"Start_Pos":2541,"End_Pos":2551,"WordSt":"tine curu\u0027","WordDisplayed":"tine curu\u0027","IdPhrase":"","Id":"113","IdFin":"","Type":0,"vectSolution":[{"Left":"ține curul","Right":"ține curul"}],"ExplicationSolution":"Corectez exprimarea.","EstSuggestion":false,"Vect_SolId":[],"IsUnknownProperNoun":false,"IsAnothA":false,"VectOtherResults":[]}},{"IndexPar":0,"LeftPos":2555,"RightPos":2560,"MotSolution":{"Start_Pos":2555,"End_Pos":2560,"WordSt":"baraj","WordDisplayed":"baraj","IdPhrase":"","Id":"114","IdFin":"","Type":0,"vectSolution":[{"Left":"baraj!","Right":"baraj!"}],"ExplicationSolution":"Corectez exprimarea.","EstSuggestion":false,"Vect_SolId":[],"IsUnknownProperNoun":false,"IsAnothA":false,"VectOtherResults":[]}},{"IndexPar":0,"LeftPos":2562,"RightPos":2578,"MotSolution":{"Start_Pos":2562,"End_Pos":2578,"WordSt":"Taci cacatule ca","WordDisplayed":"Taci cacatule ca","IdPhrase":"","Id":"115","IdFin":"","Type":0,"vectSolution":[{"Left":"Taci, căcatule, că","Right":"Taci, căcatule, că"}],"ExplicationSolution":"Corectez exprimarea.","EstSuggestion":false,"Vect_SolId":[],"IsUnknownProperNoun":false,"IsAnothA":false,"VectOtherResults":[]}},{"IndexPar":0,"LeftPos":2586,"RightPos":2601,"MotSolution":{"Start_Pos":2586,"End_Pos":2601,"WordSt":"acu se\u0027ndreapta","WordDisplayed":"acu se\u0027ndreapta","IdPhrase":"","Id":"116","IdFin":"","Type":0,"vectSolution":[{"Left":"acu\u0027 se-ndreaptă","Right":"acu\u0027 se-ndreaptă"}],"ExplicationSolution":"Corectez exprimarea.","EstSuggestion":false,"Vect_SolId":[],"IsUnknownProperNoun":false,"IsAnothA":false,"VectOtherResults":[]}},{"IndexPar":0,"LeftPos":2608,"RightPos":2618,"MotSolution":{"Start_Pos":2608,"End_Pos":2618,"WordSt":"catre casa","WordDisplayed":"catre casa","IdPhrase":"","Id":"117","IdFin":"","Type":0,"vectSolution":[{"Left":"către casă","Right":"către casă"}],"ExplicationSolution":"Corectez exprimarea.","EstSuggestion":false,"Vect_SolId":[],"IsUnknownProperNoun":false,"IsAnothA":false,"VectOtherResults":[]}},{"IndexPar":0,"LeftPos":2624,"RightPos":2628,"MotSolution":{"Start_Pos":2624,"End_Pos":2628,"WordSt":"pita","WordDisplayed":"pita","IdPhrase":"","Id":"118","IdFin":"","Type":0,"vectSolution":[{"Left":"pită","Right":"pită"}],"ExplicationSolution":"Corectez exprimarea.","EstSuggestion":false,"Vect_SolId":[],"IsUnknownProperNoun":false,"IsAnothA":false,"VectOtherResults":[]}},{"IndexPar":0,"LeftPos":2635,"RightPos":2645,"MotSolution":{"Start_Pos":2635,"End_Pos":2645,"WordSt":"mine dracu","WordDisplayed":"mine dracu","IdPhrase":"","Id":"119","IdFin":"","Type":0,"vectSolution":[{"Left":"mine. Dracu","Right":"mine. Dracu"}],"ExplicationSolution":"Corectez exprimarea.","EstSuggestion":false,"Vect_SolId":[],"IsUnknownProperNoun":false,"IsAnothA":false,"VectOtherResults":[]}},{"IndexPar":0,"LeftPos":2649,"RightPos":2675,"MotSolution":{"Start_Pos":2649,"End_Pos":2675,"WordSt":"saracie caca\u0027ti\u0027as fruntea","WordDisplayed":"saracie caca\u0027ti\u0027as fruntea","IdPhrase":"","Id":"120","IdFin":"","Type":0,"vectSolution":[{"Left":"sărăcie, căca-ți-aș fruntea!","Right":"sărăcie, căca-ți-aș fruntea!"}],"ExplicationSolution":"Corectez exprimarea.","EstSuggestion":false,"Vect_SolId":[],"IsUnknownProperNoun":false,"IsAnothA":false,"VectOtherResults":[]}},{"IndexPar":0,"LeftPos":2697,"RightPos":2706,"MotSolution":{"Start_Pos":2697,"End_Pos":2706,"WordSt":"si incepi","WordDisplayed":"si incepi","IdPhrase":"","Id":"121","IdFin":"","Type":0,"vectSolution":[{"Left":"și începi","Right":"și începi"}],"ExplicationSolution":"Corectez exprimarea.","EstSuggestion":false,"Vect_SolId":[],"IsUnknownProperNoun":false,"IsAnothA":false,"VectOtherResults":[]}},{"IndexPar":0,"LeftPos":2713,"RightPos":2725,"MotSolution":{"Start_Pos":2713,"End_Pos":2725,"WordSt":"radacina! ce","WordDisplayed":"radacina! ce","IdPhrase":"","Id":"122","IdFin":"","Type":0,"vectSolution":[{"Left":"rădăcină! Ce","Right":"rădăcină! Ce"}],"ExplicationSolution":"Corectez exprimarea.","EstSuggestion":false,"Vect_SolId":[],"IsUnknownProperNoun":false,"IsAnothA":false,"VectOtherResults":[]}},{"IndexPar":0,"LeftPos":2731,"RightPos":2738,"MotSolution":{"Start_Pos":2731,"End_Pos":2738,"WordSt":"mea ma,","WordDisplayed":"mea ma,","IdPhrase":"","Id":"123","IdFin":"","Type":0,"vectSolution":[{"Left":"mea,","Right":"mea,"}],"ExplicationSolution":"Corectez exprimarea.","EstSuggestion":false,"Vect_SolId":[],"IsUnknownProperNoun":false,"IsAnothA":false,"VectOtherResults":[]}},{"IndexPar":0,"LeftPos":2760,"RightPos":2765,"MotSolution":{"Start_Pos":2760,"End_Pos":2765,"WordSt":"grija","WordDisplayed":"grija","IdPhrase":"","Id":"124","IdFin":"","Type":0,"vectSolution":[{"Left":"grijă","Right":"grijă"}],"ExplicationSolution":"Corectez exprimarea.","EstSuggestion":false,"Vect_SolId":[],"IsUnknownProperNoun":false,"IsAnothA":false,"VectOtherResults":[]}},{"IndexPar":0,"LeftPos":2782,"RightPos":2786,"MotSolution":{"Start_Pos":2782,"End_Pos":2786,"WordSt":"oara","WordDisplayed":"oara","IdPhrase":"","Id":"125","IdFin":"","Type":0,"vectSolution":[{"Left":"oară","Right":"oară"}],"ExplicationSolution":"Corectez exprimarea.","EstSuggestion":false,"Vect_SolId":[],"IsUnknownProperNoun":false,"IsAnothA":false,"VectOtherResults":[]}},{"IndexPar":0,"LeftPos":2792,"RightPos":2799,"MotSolution":{"Start_Pos":2792,"End_Pos":2799,"WordSt":"supt- o","WordDisplayed":"supt- o","IdPhrase":"","Id":"126","IdFin":"","Type":0,"vectSolution":[{"Left":"supt-o","Right":"supt-o"}],"ExplicationSolution":"Corectez exprimarea.","EstSuggestion":false,"Vect_SolId":[],"IsUnknownProperNoun":false,"IsAnothA":false,"VectOtherResults":[]}},{"IndexPar":0,"LeftPos":2816,"RightPos":2818,"MotSolution":{"Start_Pos":2816,"End_Pos":2818,"WordSt":"si","WordDisplayed":"si","IdPhrase":"","Id":"127","IdFin":"","Type":0,"vectSolution":[{"Left":"și","Right":"și"}],"ExplicationSolution":"Corectez exprimarea.","EstSuggestion":false,"Vect_SolId":[],"IsUnknownProperNoun":false,"IsAnothA":false,"VectOtherResults":[]}},{"IndexPar":0,"LeftPos":2841,"RightPos":2846,"MotSolution":{"Start_Pos":2841,"End_Pos":2846,"WordSt":"sa ma","WordDisplayed":"sa ma","IdPhrase":"","Id":"128","IdFin":"","Type":0,"vectSolution":[{"Left":"să mă","Right":"să mă"}],"ExplicationSolution":"Corectez exprimarea.","EstSuggestion":false,"Vect_SolId":[],"IsUnknownProperNoun":false,"IsAnothA":false,"VectOtherResults":[]}},{"IndexPar":0,"LeftPos":2855,"RightPos":2861,"MotSolution":{"Start_Pos":2855,"End_Pos":2861,"WordSt":"gaoaza","WordDisplayed":"gaoaza","IdPhrase":"","Id":"129","IdFin":"","Type":0,"vectSolution":[{"Left":"gaoază,","Right":"gaoază,"}],"ExplicationSolution":"Corectez exprimarea.","EstSuggestion":false,"Vect_SolId":[],"IsUnknownProperNoun":false,"IsAnothA":false,"VectOtherResults":[]}},{"IndexPar":0,"LeftPos":2873,"RightPos":2886,"MotSolution":{"Start_Pos":2873,"End_Pos":2886,"WordSt":"pretentioasa!","WordDisplayed":"pretentioasa!","IdPhrase":"","Id":"130","IdFin":"","Type":0,"vectSolution":[{"Left":"pretențioasă!","Right":"pretențioasă!"}],"ExplicationSolution":"Corectez exprimarea.","EstSuggestion":false,"Vect_SolId":[],"IsUnknownProperNoun":false,"IsAnothA":false,"VectOtherResults":[]}},{"IndexPar":0,"LeftPos":2888,"RightPos":2896,"MotSolution":{"Start_Pos":2888,"End_Pos":2896,"WordSt":"Drequ da","WordDisplayed":"Drequ da","IdPhrase":"","Id":"131","IdFin":"","Type":0,"vectSolution":[{"Left":"Drac dă","Right":"Drac dă"}],"ExplicationSolution":"Corectez exprimarea.","EstSuggestion":false,"Vect_SolId":[],"IsUnknownProperNoun":false,"IsAnothA":false,"VectOtherResults":[]}},{"IndexPar":0,"LeftPos":2907,"RightPos":2916,"MotSolution":{"Start_Pos":2907,"End_Pos":2916,"WordSt":"libidinos","WordDisplayed":"libidinos","IdPhrase":"","Id":"132","IdFin":"","Type":0,"vectSolution":[{"Left":"libidinos,","Right":"libidinos,"}],"ExplicationSolution":"Corectez exprimarea.","EstSuggestion":false,"Vect_SolId":[],"IsUnknownProperNoun":false,"IsAnothA":false,"VectOtherResults":[]}},{"IndexPar":0,"LeftPos":2920,"RightPos":2937,"MotSolution":{"Start_Pos":2920,"End_Pos":2937,"WordSt":"ce cacat pa varza","WordDisplayed":"ce cacat pa varza","IdPhrase":"","Id":"133","IdFin":"","Type":0,"vectSolution":[{"Left":"ce, rahat, pe varză","Right":"ce, rahat, pe varză"}],"ExplicationSolution":"Corectez exprimarea.","EstSuggestion":false,"Vect_SolId":[],"IsUnknownProperNoun":false,"IsAnothA":false,"VectOtherResults":[]}},{"IndexPar":0,"LeftPos":2949,"RightPos":2960,"MotSolution":{"Start_Pos":2949,"End_Pos":2960,"WordSt":"pa priza ma","WordDisplayed":"pa priza ma","IdPhrase":"","Id":"134","IdFin":"","Type":0,"vectSolution":[{"Left":"pe priză, mă","Right":"pe priză, mă"}],"ExplicationSolution":"Corectez exprimarea.","EstSuggestion":false,"Vect_SolId":[],"IsUnknownProperNoun":false,"IsAnothA":false,"VectOtherResults":[]}},{"IndexPar":0,"LeftPos":2968,"RightPos":2980,"MotSolution":{"Start_Pos":2968,"End_Pos":2980,"WordSt":"uzat ? Dațaș","WordDisplayed":"uzat ? Dațaș","IdPhrase":"","Id":"135","IdFin":"","Type":0,"vectSolution":[{"Left":"uzat? Da-țaș","Right":"uzat? Da-țaș"}],"ExplicationSolution":"Corectez exprimarea.","EstSuggestion":false,"Vect_SolId":[],"IsUnknownProperNoun":false,"IsAnothA":false,"VectOtherResults":[]}},{"IndexPar":0,"LeftPos":2986,"RightPos":2992,"MotSolution":{"Start_Pos":2986,"End_Pos":2992,"WordSt":"amanet","WordDisplayed":"amanet","IdPhrase":"","Id":"136","IdFin":"","Type":0,"vectSolution":[{"Left":"amanet,","Right":"amanet,"}],"ExplicationSolution":"Corectez exprimarea.","EstSuggestion":false,"Vect_SolId":[],"IsUnknownProperNoun":false,"IsAnothA":false,"VectOtherResults":[]}},{"IndexPar":0,"LeftPos":3002,"RightPos":3009,"MotSolution":{"Start_Pos":3002,"End_Pos":3009,"WordSt":"genital","WordDisplayed":"genital","IdPhrase":"","Id":"137","IdFin":"","Type":0,"vectSolution":[{"Left":"genital!","Right":"genital!"}],"ExplicationSolution":"Corectez exprimarea.","EstSuggestion":false,"Vect_SolId":[],"IsUnknownProperNoun":false,"IsAnothA":false,"VectOtherResults":[]}},{"IndexPar":0,"LeftPos":3015,"RightPos":3020,"MotSolution":{"Start_Pos":3015,"End_Pos":3020,"WordSt":"luati","WordDisplayed":"luati","IdPhrase":"","Id":"138","IdFin":"","Type":0,"vectSolution":[{"Left":"luați","Right":"luați"}],"ExplicationSolution":"Corectez exprimarea.","EstSuggestion":false,"Vect_SolId":[],"IsUnknownProperNoun":false,"IsAnothA":false,"VectOtherResults":[]}},{"IndexPar":0,"LeftPos":3023,"RightPos":3040,"MotSolution":{"Start_Pos":3023,"End_Pos":3040,"WordSt":"frana si ducețiva","WordDisplayed":"frana si ducețiva","IdPhrase":"","Id":"139","IdFin":"","Type":0,"vectSolution":[{"Left":"frână și duceți-vă","Right":"frână și duceți-vă"}],"ExplicationSolution":"Corectez exprimarea.","EstSuggestion":false,"Vect_SolId":[],"IsUnknownProperNoun":false,"IsAnothA":false,"VectOtherResults":[]}},{"IndexPar":0,"LeftPos":3044,"RightPos":3046,"MotSolution":{"Start_Pos":3044,"End_Pos":3046,"WordSt":"va","WordDisplayed":"va","IdPhrase":"","Id":"140","IdFin":"","Type":0,"vectSolution":[{"Left":"vă","Right":"vă"}],"ExplicationSolution":"Corectez exprimarea.","EstSuggestion":false,"Vect_SolId":[],"IsUnknownProperNoun":false,"IsAnothA":false,"VectOtherResults":[]}},{"IndexPar":0,"LeftPos":3098,"RightPos":3118,"MotSolution":{"Start_Pos":3098,"End_Pos":3118,"WordSt":"Floreasca luati cate","WordDisplayed":"Floreasca luati cate","IdPhrase":"","Id":"141","IdFin":"","Type":0,"vectSolution":[{"Left":"Floreasca. Luați câte","Right":"Floreasca. Luați câte"}],"ExplicationSolution":"Corectez exprimarea.","EstSuggestion":false,"Vect_SolId":[],"IsUnknownProperNoun":false,"IsAnothA":false,"VectOtherResults":[]}},{"IndexPar":0,"LeftPos":3131,"RightPos":3157,"MotSolution":{"Start_Pos":3131,"End_Pos":3157,"WordSt":"si niste vodka si va trece","WordDisplayed":"si niste vodka si va trece","IdPhrase":"","Id":"142","IdFin":"","Type":0,"vectSolution":[{"Left":"și niște vodcă și vă trece.","Right":"și niște vodcă și vă trece."}],"ExplicationSolution":"Corectez exprimarea.","EstSuggestion":false,"Vect_SolId":[],"IsUnknownProperNoun":false,"IsAnothA":false,"VectOtherResults":[]}},{"IndexPar":0,"LeftPos":3159,"RightPos":3167,"MotSolution":{"Start_Pos":3159,"End_Pos":3167,"WordSt":"Ma-ta ii","WordDisplayed":"Ma-ta ii","IdPhrase":"","Id":"143","IdFin":"","Type":0,"vectSolution":[{"Left":"Ma-ta-i","Right":"Ma-ta-i"}],"ExplicationSolution":"Corectez exprimarea.","EstSuggestion":false,"Vect_SolId":[],"IsUnknownProperNoun":false,"IsAnothA":false,"VectOtherResults":[]}},{"IndexPar":0,"LeftPos":3176,"RightPos":3184,"MotSolution":{"Start_Pos":3176,"End_Pos":3184,"WordSt":"cacofila","WordDisplayed":"cacofila","IdPhrase":"","Id":"144","IdFin":"","Type":0,"vectSolution":[{"Left":"cacofilă:","Right":"cacofilă:"}],"ExplicationSolution":"Corectez exprimarea.","EstSuggestion":false,"Vect_SolId":[],"IsUnknownProperNoun":false,"IsAnothA":false,"VectOtherResults":[]}},{"IndexPar":0,"LeftPos":3197,"RightPos":3202,"MotSolution":{"Start_Pos":3197,"End_Pos":3202,"WordSt":"cacat","WordDisplayed":"cacat","IdPhrase":"","Id":"145","IdFin":"","Type":0,"vectSolution":[{"Left":"rahat,","Right":"rahat,"}],"ExplicationSolution":"Corectez exprimarea.","EstSuggestion":false,"Vect_SolId":[],"IsUnknownProperNoun":false,"IsAnothA":false,"VectOtherResults":[]}},{"IndexPar":0,"LeftPos":3207,"RightPos":3209,"MotSolution":{"Start_Pos":3207,"End_Pos":3209,"WordSt":"si","WordDisplayed":"si","IdPhrase":"","Id":"146","IdFin":"","Type":0,"vectSolution":[{"Left":"și","Right":"și"}],"ExplicationSolution":"Corectez exprimarea.","EstSuggestion":false,"Vect_SolId":[],"IsUnknownProperNoun":false,"IsAnothA":false,"VectOtherResults":[]}},{"IndexPar":0,"LeftPos":3218,"RightPos":3220,"MotSolution":{"Start_Pos":3218,"End_Pos":3220,"WordSt":"le","WordDisplayed":"le","IdPhrase":"","Id":"147","IdFin":"","Type":0,"vectSolution":[{"Left":"el","Right":"el"}],"ExplicationSolution":"Corectez exprimarea.","EstSuggestion":false,"Vect_SolId":[],"IsUnknownProperNoun":false,"IsAnothA":false,"VectOtherResults":[]}},{"IndexPar":0,"LeftPos":3224,"RightPos":3228,"MotSolution":{"Start_Pos":3224,"End_Pos":3228,"WordSt":"gura","WordDisplayed":"gura","IdPhrase":"","Id":"148","IdFin":"","Type":0,"vectSolution":[{"Left":"gura!","Right":"gura!"}],"ExplicationSolution":"Corectez exprimarea.","EstSuggestion":false,"Vect_SolId":[],"IsUnknownProperNoun":false,"IsAnothA":false,"VectOtherResults":[]}},{"IndexPar":0,"LeftPos":3234,"RightPos":3247,"MotSolution":{"Start_Pos":3234,"End_Pos":3247,"WordSt":"parțarilor ma","WordDisplayed":"parțarilor ma","IdPhrase":"","Id":"149","IdFin":"","Type":0,"vectSolution":[{"Left":"parțarilor, mă","Right":"parțarilor, mă"}],"ExplicationSolution":"Corectez exprimarea.","EstSuggestion":false,"Vect_SolId":[],"IsUnknownProperNoun":false,"IsAnothA":false,"VectOtherResults":[]}},{"IndexPar":0,"LeftPos":3275,"RightPos":3285,"MotSolution":{"Start_Pos":3275,"End_Pos":3285,"WordSt":"pa masa sa","WordDisplayed":"pa masa sa","IdPhrase":"","Id":"150","IdFin":"","Type":0,"vectSolution":[{"Left":"pe masă, să","Right":"pe masă, să"}],"ExplicationSolution":"Corectez exprimarea.","EstSuggestion":false,"Vect_SolId":[],"IsUnknownProperNoun":false,"IsAnothA":false,"VectOtherResults":[]}},{"IndexPar":0,"LeftPos":3299,"RightPos":3317,"MotSolution":{"Start_Pos":3299,"End_Pos":3317,"WordSt":"de\u0027un dejun futava","WordDisplayed":"de\u0027un dejun futava","IdPhrase":"","Id":"151","IdFin":"","Type":0,"vectSolution":[{"Left":"de-un dejun! Futu-vă","Right":"de-un dejun! Futu-vă"}],"ExplicationSolution":"Corectez exprimarea.","EstSuggestion":false,"Vect_SolId":[],"IsUnknownProperNoun":false,"IsAnothA":false,"VectOtherResults":[]}},{"IndexPar":0,"LeftPos":3325,"RightPos":3335,"MotSolution":{"Start_Pos":3325,"End_Pos":3335,"WordSt":"da maronii","WordDisplayed":"da maronii","IdPhrase":"","Id":"152","IdFin":"","Type":0,"vectSolution":[{"Left":"de maronii!","Right":"de maronii!"}],"ExplicationSolution":"Corectez exprimarea.","EstSuggestion":false,"Vect_SolId":[],"IsUnknownProperNoun":false,"IsAnothA":false,"VectOtherResults":[]}},{"IndexPar":0,"LeftPos":3339,"RightPos":3367,"MotSolution":{"Start_Pos":3339,"End_Pos":3367,"WordSt":"nesatioasa rau ma-ta, pot sa","WordDisplayed":"nesatioasa rau ma-ta, pot sa","IdPhrase":"","Id":"153","IdFin":"","Type":0,"vectSolution":[{"Left":"nesățioasă rău ma-ta. Pot să","Right":"nesățioasă rău ma-ta. Pot să"}],"ExplicationSolution":"Corectez exprimarea.","EstSuggestion":false,"Vect_SolId":[],"IsUnknownProperNoun":false,"IsAnothA":false,"VectOtherResults":[]}},{"IndexPar":0,"LeftPos":3373,"RightPos":3375,"MotSolution":{"Start_Pos":3373,"End_Pos":3375,"WordSt":"ca","WordDisplayed":"ca","IdPhrase":"","Id":"154","IdFin":"","Type":0,"vectSolution":[{"Left":"că","Right":"că"}],"ExplicationSolution":"Corectez exprimarea.","EstSuggestion":false,"Vect_SolId":[],"IsUnknownProperNoun":false,"IsAnothA":false,"VectOtherResults":[]}},{"IndexPar":0,"LeftPos":3378,"RightPos":3383,"MotSolution":{"Start_Pos":3378,"End_Pos":3383,"WordSt":"rampa","WordDisplayed":"rampa","IdPhrase":"","Id":"155","IdFin":"","Type":0,"vectSolution":[{"Left":"rampă","Right":"rampă"}],"ExplicationSolution":"Corectez exprimarea.","EstSuggestion":false,"Vect_SolId":[],"IsUnknownProperNoun":false,"IsAnothA":false,"VectOtherResults":[]}},{"IndexPar":0,"LeftPos":3402,"RightPos":3408,"MotSolution":{"Start_Pos":3402,"End_Pos":3408,"WordSt":"putori","WordDisplayed":"putori","IdPhrase":"","Id":"156","IdFin":"","Type":0,"vectSolution":[{"Left":"putori!","Right":"putori!"}],"ExplicationSolution":"Corectez exprimarea.","EstSuggestion":false,"Vect_SolId":[],"IsUnknownProperNoun":false,"IsAnothA":false,"VectOtherResults":[]}},{"IndexPar":0,"LeftPos":3410,"RightPos":3415,"MotSolution":{"Start_Pos":3410,"End_Pos":3415,"WordSt":"Davaș","WordDisplayed":"Davaș","IdPhrase":"","Id":"157","IdFin":"","Type":0,"vectSolution":[{"Left":"Da-vaș","Right":"Da-vaș"}],"ExplicationSolution":"Corectez exprimarea.","EstSuggestion":false,"Vect_SolId":[],"IsUnknownProperNoun":false,"IsAnothA":false,"VectOtherResults":[]}},{"IndexPar":0,"LeftPos":3421,"RightPos":3429,"MotSolution":{"Start_Pos":3421,"End_Pos":3429,"WordSt":"pa spate","WordDisplayed":"pa spate","IdPhrase":"","Id":"158","IdFin":"","Type":0,"vectSolution":[{"Left":"pe spate,","Right":"pe spate,"}],"ExplicationSolution":"Corectez exprimarea.","EstSuggestion":false,"Vect_SolId":[],"IsUnknownProperNoun":false,"IsAnothA":false,"VectOtherResults":[]}},{"IndexPar":0,"LeftPos":3442,"RightPos":3452,"MotSolution":{"Start_Pos":3442,"End_Pos":3452,"WordSt":"paduchioși","WordDisplayed":"paduchioși","IdPhrase":"","Id":"159","IdFin":"","Type":0,"vectSolution":[{"Left":"păduchioși","Right":"păduchioși"}],"ExplicationSolution":"Corectez exprimarea.","EstSuggestion":false,"Vect_SolId":[],"IsUnknownProperNoun":false,"IsAnothA":false,"VectOtherResults":[]}},{"IndexPar":0,"LeftPos":3456,"RightPos":3466,"MotSolution":{"Start_Pos":3456,"End_Pos":3466,"WordSt":"slobozimaș","WordDisplayed":"slobozimaș","IdPhrase":"","Id":"160","IdFin":"","Type":0,"vectSolution":[{"Left":"slobozi-maș","Right":"slobozi-maș"}],"ExplicationSolution":"Corectez exprimarea.","EstSuggestion":false,"Vect_SolId":[],"IsUnknownProperNoun":false,"IsAnothA":false,"VectOtherResults":[]}},{"IndexPar":0,"LeftPos":3474,"RightPos":3485,"MotSolution":{"Start_Pos":3474,"End_Pos":3485,"WordSt":"in buzunare","WordDisplayed":"in buzunare","IdPhrase":"","Id":"161","IdFin":"","Type":0,"vectSolution":[{"Left":"în buzunare,","Right":"în buzunare,"}],"ExplicationSolution":"Corectez exprimarea.","EstSuggestion":false,"Vect_SolId":[],"IsUnknownProperNoun":false,"IsAnothA":false,"VectOtherResults":[]}},{"IndexPar":0,"LeftPos":3489,"RightPos":3500,"MotSolution":{"Start_Pos":3489,"End_Pos":3500,"WordSt":"strangatori","WordDisplayed":"strangatori","IdPhrase":"","Id":"162","IdFin":"","Type":0,"vectSolution":[{"Left":"strângători!","Right":"strângători!"}],"ExplicationSolution":"Corectez exprimarea.","EstSuggestion":false,"Vect_SolId":[],"IsUnknownProperNoun":false,"IsAnothA":false,"VectOtherResults":[]}},{"IndexPar":0,"LeftPos":3502,"RightPos":3504,"MotSolution":{"Start_Pos":3502,"End_Pos":3504,"WordSt":"In","WordDisplayed":"In","IdPhrase":"","Id":"163","IdFin":"","Type":0,"vectSolution":[{"Left":"În","Right":"În"}],"ExplicationSolution":"Corectez exprimarea.","EstSuggestion":false,"Vect_SolId":[],"IsUnknownProperNoun":false,"IsAnothA":false,"VectOtherResults":[]}},{"IndexPar":0,"LeftPos":3521,"RightPos":3536,"MotSolution":{"Start_Pos":3521,"End_Pos":3536,"WordSt":"esti penibil sa","WordDisplayed":"esti penibil sa","IdPhrase":"","Id":"164","IdFin":"","Type":0,"vectSolution":[{"Left":"ești penibil, să","Right":"ești penibil, să"}],"ExplicationSolution":"Corectez exprimarea.","EstSuggestion":false,"Vect_SolId":[],"IsUnknownProperNoun":false,"IsAnothA":false,"VectOtherResults":[]}},{"IndexPar":0,"LeftPos":3544,"RightPos":3552,"MotSolution":{"Start_Pos":3544,"End_Pos":3552,"WordSt":"retardat","WordDisplayed":"retardat","IdPhrase":"","Id":"165","IdFin":"","Type":0,"vectSolution":[{"Left":"retardat,","Right":"retardat,"}],"ExplicationSolution":"Corectez exprimarea.","EstSuggestion":false,"Vect_SolId":[],"IsUnknownProperNoun":false,"IsAnothA":false,"VectOtherResults":[]}},{"IndexPar":0,"LeftPos":3563,"RightPos":3570,"MotSolution":{"Start_Pos":3563,"End_Pos":3570,"WordSt":"tale da","WordDisplayed":"tale da","IdPhrase":"","Id":"166","IdFin":"","Type":0,"vectSolution":[{"Left":"tale, da\u0027","Right":"tale, da\u0027"}],"ExplicationSolution":"Corectez exprimarea.","EstSuggestion":false,"Vect_SolId":[],"IsUnknownProperNoun":false,"IsAnothA":false,"VectOtherResults":[]}},{"IndexPar":0,"LeftPos":3575,"RightPos":3590,"MotSolution":{"Start_Pos":3575,"End_Pos":3590,"WordSt":"cacatu incearca","WordDisplayed":"cacatu incearca","IdPhrase":"","Id":"167","IdFin":"","Type":0,"vectSolution":[{"Left":"rahatul încearcă","Right":"rahatul încearcă"}],"ExplicationSolution":"Corectez exprimarea.","EstSuggestion":false,"Vect_SolId":[],"IsUnknownProperNoun":false,"IsAnothA":false,"VectOtherResults":[]}},{"IndexPar":0,"LeftPos":3597,"RightPos":3599,"MotSolution":{"Start_Pos":3597,"End_Pos":3599,"WordSt":"sa","WordDisplayed":"sa","IdPhrase":"","Id":"168","IdFin":"","Type":0,"vectSolution":[{"Left":"să","Right":"să"}],"ExplicationSolution":"Corectez exprimarea.","EstSuggestion":false,"Vect_SolId":[],"IsUnknownProperNoun":false,"IsAnothA":false,"VectOtherResults":[]}},{"IndexPar":0,"LeftPos":3613,"RightPos":3625,"MotSolution":{"Start_Pos":3613,"End_Pos":3625,"WordSt":"succint, mai","WordDisplayed":"succint, mai","IdPhrase":"","Id":"169","IdFin":"","Type":0,"vectSolution":[{"Left":"succint. Mai","Right":"succint. Mai"}],"ExplicationSolution":"Corectez exprimarea.","EstSuggestion":false,"Vect_SolId":[],"IsUnknownProperNoun":false,"IsAnothA":false,"VectOtherResults":[]}},{"IndexPar":0,"LeftPos":3637,"RightPos":3652,"MotSolution":{"Start_Pos":3637,"End_Pos":3652,"WordSt":"sa\u0027mi suji pula","WordDisplayed":"sa\u0027mi suji pula","IdPhrase":"","Id":"170","IdFin":"","Type":0,"vectSolution":[{"Left":"să-mi sugi pula,","Right":"să-mi sugi pula,"}],"ExplicationSolution":"Corectez exprimarea.","EstSuggestion":false,"Vect_SolId":[],"IsUnknownProperNoun":false,"IsAnothA":false,"VectOtherResults":[]}},{"IndexPar":0,"LeftPos":3656,"RightPos":3663,"MotSolution":{"Start_Pos":3656,"End_Pos":3663,"WordSt":"ramolit","WordDisplayed":"ramolit","IdPhrase":"","Id":"171","IdFin":"","Type":0,"vectSolution":[{"Left":"ramolit!","Right":"ramolit!"}],"ExplicationSolution":"Corectez exprimarea.","EstSuggestion":false,"Vect_SolId":[],"IsUnknownProperNoun":false,"IsAnothA":false,"VectOtherResults":[]}},{"IndexPar":0,"LeftPos":3665,"RightPos":3695,"MotSolution":{"Start_Pos":3665,"End_Pos":3695,"WordSt":"Ma-ta daca i-as trage-o in git","WordDisplayed":"Ma-ta daca i-as trage-o in git","IdPhrase":"","Id":"172","IdFin":"","Type":0,"vectSolution":[{"Left":"Ma-ta, dacă i-aș trage-o-n gât,","Right":"Ma-ta, dacă i-aș trage-o-n gât,"}],"ExplicationSolution":"Corectez exprimarea.","EstSuggestion":false,"Vect_SolId":[],"IsUnknownProperNoun":false,"IsAnothA":false,"VectOtherResults":[]}},{"IndexPar":0,"LeftPos":3701,"RightPos":3705,"MotSolution":{"Start_Pos":3701,"End_Pos":3705,"WordSt":"lasa","WordDisplayed":"lasa","IdPhrase":"","Id":"173","IdFin":"","Type":0,"vectSolution":[{"Left":"lăsa","Right":"lăsa"}],"ExplicationSolution":"Corectez exprimarea.","EstSuggestion":false,"Vect_SolId":[],"IsUnknownProperNoun":false,"IsAnothA":false,"VectOtherResults":[]}},{"IndexPar":0,"LeftPos":3709,"RightPos":3714,"MotSolution":{"Start_Pos":3709,"End_Pos":3714,"WordSt":"tacto","WordDisplayed":"tacto","IdPhrase":"","Id":"174","IdFin":"","Type":0,"vectSolution":[{"Left":"tac-tu","Right":"tac-tu"}],"ExplicationSolution":"Corectez exprimarea.","EstSuggestion":false,"Vect_SolId":[],"IsUnknownProperNoun":false,"IsAnothA":false,"VectOtherResults":[]}},{"IndexPar":0,"LeftPos":3742,"RightPos":3745,"MotSolution":{"Start_Pos":3742,"End_Pos":3745,"WordSt":"isi","WordDisplayed":"isi","IdPhrase":"","Id":"175","IdFin":"","Type":0,"vectSolution":[{"Left":"își","Right":"își"}],"ExplicationSolution":"Corectez exprimarea.","EstSuggestion":false,"Vect_SolId":[],"IsUnknownProperNoun":false,"IsAnothA":false,"VectOtherResults":[]}},{"IndexPar":0,"LeftPos":3766,"RightPos":3768,"MotSolution":{"Start_Pos":3766,"End_Pos":3768,"WordSt":"ca","WordDisplayed":"ca","IdPhrase":"","Id":"176","IdFin":"","Type":0,"vectSolution":[{"Left":"că","Right":"că"}],"ExplicationSolution":"Corectez exprimarea.","EstSuggestion":false,"Vect_SolId":[],"IsUnknownProperNoun":false,"IsAnothA":false,"VectOtherResults":[]}},{"IndexPar":0,"LeftPos":3797,"RightPos":3806,"MotSolution":{"Start_Pos":3797,"End_Pos":3806,"WordSt":"cacaciosu","WordDisplayed":"cacaciosu","IdPhrase":"","Id":"177","IdFin":"","Type":0,"vectSolution":[{"Left":"căcăciosul","Right":"căcăciosul"}],"ExplicationSolution":"Corectez exprimarea.","EstSuggestion":false,"Vect_SolId":[],"IsUnknownProperNoun":false,"IsAnothA":false,"VectOtherResults":[]}},{"IndexPar":0,"LeftPos":3820,"RightPos":3829,"MotSolution":{"Start_Pos":3820,"End_Pos":3829,"WordSt":"esti, s-o","WordDisplayed":"esti, s-o","IdPhrase":"","Id":"178","IdFin":"","Type":0,"vectSolution":[{"Left":"ești. S-o","Right":"ești. S-o"}],"ExplicationSolution":"Corectez exprimarea.","EstSuggestion":false,"Vect_SolId":[],"IsUnknownProperNoun":false,"IsAnothA":false,"VectOtherResults":[]}},{"IndexPar":0,"LeftPos":3843,"RightPos":3845,"MotSolution":{"Start_Pos":3843,"End_Pos":3845,"WordSt":"in","WordDisplayed":"in","IdPhrase":"","Id":"179","IdFin":"","Type":0,"vectSolution":[{"Left":"în","Right":"în"}],"ExplicationSolution":"Corectez exprimarea.","EstSuggestion":false,"Vect_SolId":[],"IsUnknownProperNoun":false,"IsAnothA":false,"VectOtherResults":[]}},{"IndexPar":0,"LeftPos":3851,"RightPos":3856,"MotSolution":{"Start_Pos":3851,"End_Pos":3856,"WordSt":"rambo","WordDisplayed":"rambo","IdPhrase":"","Id":"180","IdFin":"","Type":0,"vectSolution":[{"Left":"Rambo!","Right":"Rambo!"}],"ExplicationSolution":"Corectez exprimarea.","EstSuggestion":false,"Vect_SolId":[],"IsUnknownProperNoun":false,"IsAnothA":false,"VectOtherResults":[]}},{"IndexPar":0,"LeftPos":3858,"RightPos":3864,"MotSolution":{"Start_Pos":3858,"End_Pos":3864,"WordSt":"Baga-i","WordDisplayed":"Baga-i","IdPhrase":"","Id":"181","IdFin":"","Type":0,"vectSolution":[{"Left":"Bagă-i","Right":"Bagă-i"}],"ExplicationSolution":"Corectez exprimarea.","EstSuggestion":false,"Vect_SolId":[],"IsUnknownProperNoun":false,"IsAnothA":false,"VectOtherResults":[]}},{"IndexPar":0,"LeftPos":3876,"RightPos":3886,"MotSolution":{"Start_Pos":3876,"End_Pos":3886,"WordSt":"grenada in","WordDisplayed":"grenada in","IdPhrase":"","Id":"182","IdFin":"","Type":0,"vectSolution":[{"Left":"grenadă în","Right":"grenadă în"}],"ExplicationSolution":"Corectez exprimarea.","EstSuggestion":false,"Vect_SolId":[],"IsUnknownProperNoun":false,"IsAnothA":false,"VectOtherResults":[]}},{"IndexPar":0,"LeftPos":3891,"RightPos":3893,"MotSolution":{"Start_Pos":3891,"End_Pos":3893,"WordSt":"si","WordDisplayed":"si","IdPhrase":"","Id":"183","IdFin":"","Type":0,"vectSolution":[{"Left":"și","Right":"și"}],"ExplicationSolution":"Corectez exprimarea.","EstSuggestion":false,"Vect_SolId":[],"IsUnknownProperNoun":false,"IsAnothA":false,"VectOtherResults":[]}},{"IndexPar":0,"LeftPos":3904,"RightPos":3908,"MotSolution":{"Start_Pos":3904,"End_Pos":3908,"WordSt":"dupa","WordDisplayed":"dupa","IdPhrase":"","Id":"184","IdFin":"","Type":0,"vectSolution":[{"Left":"după","Right":"după"}],"ExplicationSolution":"Corectez exprimarea.","EstSuggestion":false,"Vect_SolId":[],"IsUnknownProperNoun":false,"IsAnothA":false,"VectOtherResults":[]}},{"IndexPar":0,"LeftPos":3925,"RightPos":3931,"MotSolution":{"Start_Pos":3925,"End_Pos":3931,"WordSt":"mortii","WordDisplayed":"mortii","IdPhrase":"","Id":"185","IdFin":"","Type":0,"vectSolution":[{"Left":"morții!","Right":"morții!"}],"ExplicationSolution":"Corectez exprimarea.","EstSuggestion":false,"Vect_SolId":[],"IsUnknownProperNoun":false,"IsAnothA":false,"VectOtherResults":[]}},{"IndexPar":0,"LeftPos":3933,"RightPos":3946,"MotSolution":{"Start_Pos":3933,"End_Pos":3946,"WordSt":"Ba limbricule","WordDisplayed":"Ba limbricule","IdPhrase":"","Id":"186","IdFin":"","Type":0,"vectSolution":[{"Left":"Bă, limbricule,","Right":"Bă, limbricule,"}],"ExplicationSolution":"Corectez exprimarea.","EstSuggestion":false,"Vect_SolId":[],"IsUnknownProperNoun":false,"IsAnothA":false,"VectOtherResults":[]}},{"IndexPar":0,"LeftPos":3958,"RightPos":3960,"MotSolution":{"Start_Pos":3958,"End_Pos":3960,"WordSt":"sa","WordDisplayed":"sa","IdPhrase":"","Id":"187","IdFin":"","Type":0,"vectSolution":[{"Left":"să","Right":"să"}],"ExplicationSolution":"Corectez exprimarea.","EstSuggestion":false,"Vect_SolId":[],"IsUnknownProperNoun":false,"IsAnothA":false,"VectOtherResults":[]}},{"IndexPar":0,"LeftPos":3965,"RightPos":3991,"MotSolution":{"Start_Pos":3965,"End_Pos":3991,"WordSt":"neaparat scoala ajutatoare","WordDisplayed":"neaparat scoala ajutatoare","IdPhrase":"","Id":"188","IdFin":"","Type":0,"vectSolution":[{"Left":"neapărat școala ajutătoare","Right":"neapărat școala ajutătoare"}],"ExplicationSolution":"Corectez exprimarea.","EstSuggestion":false,"Vect_SolId":[],"IsUnknownProperNoun":false,"IsAnothA":false,"VectOtherResults":[]}},{"IndexPar":0,"LeftPos":3998,"RightPos":4013,"MotSolution":{"Start_Pos":3998,"End_Pos":4013,"WordSt":"capat ca vad ca","WordDisplayed":"capat ca vad ca","IdPhrase":"","Id":"189","IdFin":"","Type":0,"vectSolution":[{"Left":"capăt, că văd că","Right":"capăt, că văd că"}],"ExplicationSolution":"Corectez exprimarea.","EstSuggestion":false,"Vect_SolId":[],"IsUnknownProperNoun":false,"IsAnothA":false,"VectOtherResults":[]}},{"IndexPar":0,"LeftPos":4028,"RightPos":4030,"MotSolution":{"Start_Pos":4028,"End_Pos":4030,"WordSt":"da","WordDisplayed":"da","IdPhrase":"","Id":"190","IdFin":"","Type":0,"vectSolution":[{"Left":"de","Right":"de"}],"ExplicationSolution":"Corectez exprimarea.","EstSuggestion":false,"Vect_SolId":[],"IsUnknownProperNoun":false,"IsAnothA":false,"VectOtherResults":[]}},{"IndexPar":0,"LeftPos":4040,"RightPos":4061,"MotSolution":{"Start_Pos":4040,"End_Pos":4061,"WordSt":"tai aia virgini dațaș","WordDisplayed":"tai aia virgini dațaș","IdPhrase":"","Id":"191","IdFin":"","Type":0,"vectSolution":[{"Left":"tăi ăia virgini. Da-țaș","Right":"tăi ăia virgini. Da-țaș"}],"ExplicationSolution":"Corectez exprimarea.","EstSuggestion":false,"Vect_SolId":[],"IsUnknownProperNoun":false,"IsAnothA":false,"VectOtherResults":[]}},{"IndexPar":0,"LeftPos":4067,"RightPos":4084,"MotSolution":{"Start_Pos":4067,"End_Pos":4084,"WordSt":"so\u0027nfiji pa ma-ta","WordDisplayed":"so\u0027nfiji pa ma-ta","IdPhrase":"","Id":"192","IdFin":"","Type":0,"vectSolution":[{"Left":"s-o-nfiji pe ma-ta!","Right":"s-o-nfiji pe ma-ta!"}],"ExplicationSolution":"Corectez exprimarea.","EstSuggestion":false,"Vect_SolId":[],"IsUnknownProperNoun":false,"IsAnothA":false,"VectOtherResults":[]}},{"IndexPar":0,"LeftPos":4091,"RightPos":4093,"MotSolution":{"Start_Pos":4091,"End_Pos":4093,"WordSt":"lu","WordDisplayed":"lu","IdPhrase":"","Id":"193","IdFin":"","Type":0,"vectSolution":[{"Left":"lui","Right":"lui"}],"ExplicationSolution":"Corectez exprimarea.","EstSuggestion":false,"Vect_SolId":[],"IsUnknownProperNoun":false,"IsAnothA":false,"VectOtherResults":[]}},{"IndexPar":0,"LeftPos":4100,"RightPos":4102,"MotSolution":{"Start_Pos":4100,"End_Pos":4102,"WordSt":"ca","WordDisplayed":"ca","IdPhrase":"","Id":"194","IdFin":"","Type":0,"vectSolution":[{"Left":"că","Right":"că"}],"ExplicationSolution":"Corectez exprimarea.","EstSuggestion":false,"Vect_SolId":[],"IsUnknownProperNoun":false,"IsAnothA":false,"VectOtherResults":[]}},{"IndexPar":0,"LeftPos":4127,"RightPos":4142,"MotSolution":{"Start_Pos":4127,"End_Pos":4142,"WordSt":"sa-ti plateasca","WordDisplayed":"sa-ti plateasca","IdPhrase":"","Id":"195","IdFin":"","Type":0,"vectSolution":[{"Left":"să-ți plătească","Right":"să-ți plătească"}],"ExplicationSolution":"Corectez exprimarea.","EstSuggestion":false,"Vect_SolId":[],"IsUnknownProperNoun":false,"IsAnothA":false,"VectOtherResults":[]}},{"IndexPar":0,"LeftPos":4158,"RightPos":4165,"MotSolution":{"Start_Pos":4158,"End_Pos":4165,"WordSt":"atita-i","WordDisplayed":"atita-i","IdPhrase":"","Id":"196","IdFin":"","Type":0,"vectSolution":[{"Left":"atâta-i","Right":"atâta-i"}],"ExplicationSolution":"Corectez exprimarea.","EstSuggestion":false,"Vect_SolId":[],"IsUnknownProperNoun":false,"IsAnothA":false,"VectOtherResults":[]}},{"IndexPar":0,"LeftPos":4169,"RightPos":4176,"MotSolution":{"Start_Pos":4169,"End_Pos":4176,"WordSt":"mare! !","WordDisplayed":"mare! !","IdPhrase":"","Id":"197","IdFin":"","Type":0,"vectSolution":[{"Left":"mare!!","Right":"mare!!"}],"ExplicationSolution":"Corectez exprimarea.","EstSuggestion":false,"Vect_SolId":[],"IsUnknownProperNoun":false,"IsAnothA":false,"VectOtherResults":[]}},{"IndexPar":0,"LeftPos":4178,"RightPos":4181,"MotSolution":{"Start_Pos":4178,"End_Pos":4181,"WordSt":"! !","WordDisplayed":"! !","IdPhrase":"","Id":"198","IdFin":"","Type":0,"vectSolution":[{"Left":"!!","Right":"!!"}],"ExplicationSolution":"Corectez exprimarea.","EstSuggestion":false,"Vect_SolId":[],"IsUnknownProperNoun":false,"IsAnothA":false,"VectOtherResults":[]}},{"IndexPar":0,"LeftPos":4183,"RightPos":4186,"MotSolution":{"Start_Pos":4183,"End_Pos":4186,"WordSt":"! !","WordDisplayed":"! !","IdPhrase":"","Id":"199","IdFin":"","Type":0,"vectSolution":[{"Left":"!!","Right":"!!"}],"ExplicationSolution":"Corectez exprimarea.","EstSuggestion":false,"Vect_SolId":[],"IsUnknownProperNoun":false,"IsAnothA":false,"VectOtherResults":[]}},{"IndexPar":0,"LeftPos":4209,"RightPos":4211,"MotSolution":{"Start_Pos":4209,"End_Pos":4211,"WordSt":"to","WordDisplayed":"to","IdPhrase":"","Id":"200","IdFin":"","Type":0,"vectSolution":[{"Left":"să","Right":"să"}],"ExplicationSolution":"Corectez exprimarea.","EstSuggestion":false,"Vect_SolId":[],"IsUnknownProperNoun":false,"IsAnothA":false,"VectOtherResults":[]}},{"IndexPar":0,"LeftPos":4226,"RightPos":4238,"MotSolution":{"Start_Pos":4226,"End_Pos":4238,"WordSt":"antirabie ca","WordDisplayed":"antirabie ca","IdPhrase":"","Id":"201","IdFin":"","Type":0,"vectSolution":[{"Left":"antirabic, că","Right":"antirabic, că"}],"ExplicationSolution":"Corectez exprimarea.","EstSuggestion":false,"Vect_SolId":[],"IsUnknownProperNoun":false,"IsAnothA":false,"VectOtherResults":[]}},{"IndexPar":0,"LeftPos":4262,"RightPos":4266,"MotSolution":{"Start_Pos":4262,"End_Pos":4266,"WordSt":"gura","WordDisplayed":"gura","IdPhrase":"","Id":"202","IdFin":"","Type":0,"vectSolution":[{"Left":"gură","Right":"gură"}],"ExplicationSolution":"Corectez exprimarea.","EstSuggestion":false,"Vect_SolId":[],"IsUnknownProperNoun":false,"IsAnothA":false,"VectOtherResults":[]}},{"IndexPar":0,"LeftPos":4277,"RightPos":4309,"MotSolution":{"Start_Pos":4277,"End_Pos":4309,"WordSt":"protectia mediului(animalelor ca","WordDisplayed":"protectia mediului(animalelor ca","IdPhrase":"","Id":"203","IdFin":"","Type":0,"vectSolution":[{"Left":"protecția mediului (animalelor, că","Right":"protecția mediului (animalelor, că"}],"ExplicationSolution":"Corectez exprimarea.","EstSuggestion":false,"Vect_SolId":[],"IsUnknownProperNoun":false,"IsAnothA":false,"VectOtherResults":[]}},{"IndexPar":0,"LeftPos":4317,"RightPos":4322,"MotSolution":{"Start_Pos":4317,"End_Pos":4322,"WordSt":"mata)","WordDisplayed":"mata)","IdPhrase":"","Id":"204","IdFin":"","Type":0,"vectSolution":[{"Left":"ma-ta).","Right":"ma-ta)."}],"ExplicationSolution":"Corectez exprimarea.","EstSuggestion":false,"Vect_SolId":[],"IsUnknownProperNoun":false,"IsAnothA":false,"VectOtherResults":[]}},{"IndexPar":0,"LeftPos":4324,"RightPos":4333,"MotSolution":{"Start_Pos":4324,"End_Pos":4333,"WordSt":"Proasta-i","WordDisplayed":"Proasta-i","IdPhrase":"","Id":"205","IdFin":"","Type":0,"vectSolution":[{"Left":"Proastă-i","Right":"Proastă-i"}],"ExplicationSolution":"Corectez exprimarea.","EstSuggestion":false,"Vect_SolId":[],"IsUnknownProperNoun":false,"IsAnothA":false,"VectOtherResults":[]}},{"IndexPar":0,"LeftPos":4343,"RightPos":4350,"MotSolution":{"Start_Pos":4343,"End_Pos":4350,"WordSt":"supt ca","WordDisplayed":"supt ca","IdPhrase":"","Id":"206","IdFin":"","Type":0,"vectSolution":[{"Left":"supt, că","Right":"supt, că"}],"ExplicationSolution":"Corectez exprimarea.","EstSuggestion":false,"Vect_SolId":[],"IsUnknownProperNoun":false,"IsAnothA":false,"VectOtherResults":[]}},{"IndexPar":0,"LeftPos":4361,"RightPos":4369,"MotSolution":{"Start_Pos":4361,"End_Pos":4369,"WordSt":"viata si","WordDisplayed":"viata si","IdPhrase":"","Id":"207","IdFin":"","Type":0,"vectSolution":[{"Left":"viață și","Right":"viață și"}],"ExplicationSolution":"Corectez exprimarea.","EstSuggestion":false,"Vect_SolId":[],"IsUnknownProperNoun":false,"IsAnothA":false,"VectOtherResults":[]}},{"IndexPar":0,"LeftPos":4374,"RightPos":4387,"MotSolution":{"Start_Pos":4374,"End_Pos":4387,"WordSt":"trabant aveti","WordDisplayed":"trabant aveti","IdPhrase":"","Id":"208","IdFin":"","Type":0,"vectSolution":[{"Left":"Trabant aveți!","Right":"Trabant aveți!"}],"ExplicationSolution":"Corectez exprimarea.","EstSuggestion":false,"Vect_SolId":[],"IsUnknownProperNoun":false,"IsAnothA":false,"VectOtherResults":[]}},{"IndexPar":0,"LeftPos":4394,"RightPos":4396,"MotSolution":{"Start_Pos":4394,"End_Pos":4396,"WordSt":"ca","WordDisplayed":"ca","IdPhrase":"","Id":"209","IdFin":"","Type":0,"vectSolution":[{"Left":"că","Right":"că"}],"ExplicationSolution":"Corectez exprimarea.","EstSuggestion":false,"Vect_SolId":[],"IsUnknownProperNoun":false,"IsAnothA":false,"VectOtherResults":[]}},{"IndexPar":0,"LeftPos":4405,"RightPos":4413,"MotSolution":{"Start_Pos":4405,"End_Pos":4413,"WordSt":"uzata ca","WordDisplayed":"uzata ca","IdPhrase":"","Id":"210","IdFin":"","Type":0,"vectSolution":[{"Left":"uzată, că","Right":"uzată, că"}],"ExplicationSolution":"Corectez exprimarea.","EstSuggestion":false,"Vect_SolId":[],"IsUnknownProperNoun":false,"IsAnothA":false,"VectOtherResults":[]}},{"IndexPar":0,"LeftPos":4428,"RightPos":4431,"MotSolution":{"Start_Pos":4428,"End_Pos":4431,"WordSt":"rau","WordDisplayed":"rau","IdPhrase":"","Id":"211","IdFin":"","Type":0,"vectSolution":[{"Left":"rău","Right":"rău"}],"ExplicationSolution":"Corectez exprimarea.","EstSuggestion":false,"Vect_SolId":[],"IsUnknownProperNoun":false,"IsAnothA":false,"VectOtherResults":[]}},{"IndexPar":0,"LeftPos":4435,"RightPos":4445,"MotSolution":{"Start_Pos":4435,"End_Pos":4445,"WordSt":"mos gerila","WordDisplayed":"mos gerila","IdPhrase":"","Id":"212","IdFin":"","Type":0,"vectSolution":[{"Left":"Moș Gerilă.","Right":"Moș Gerilă."}],"ExplicationSolution":"Corectez exprimarea.","EstSuggestion":false,"Vect_SolId":[],"IsUnknownProperNoun":false,"IsAnothA":false,"VectOtherResults":[]}}]},"DisplayPremiumPanel":false}